{
  "anuvaka": "TS 4.7.4",
  "verses": [
    {
      "index": "TS 4.7.4.1",
      "samhita": "Urkca# mE sUqnRutA# ca mEq paya#Sca mEq rasa#Sca mE GRuqtaM ca# mEq madhu# ca mEq sagdhi#Sca mEq sapI#tiSca mE kRuqShiSca# mEq vRuShTi#Sca mEq jaitraM# ca maq audBi#dyaM ca mE raqyiSca# mEq rAya#Sca mE puqShTaM ca# mEq puShTi#Sca mE viqBu ca# - [  ] 7",
      "citta": {
        "section_count": "(7)",
        "anuvaka": "(A4)"
      }
    },
    {
      "index": "TS 4.7.4.2",
      "samhita": "mE praqBu ca# mE baqhu ca# mEq BUya#Sca mE pUqrNaM ca# mE pUqrNata#raM caq mE &kShi#tiSca mEq kUya#vAScaq mE&nnaM# caq mE &kShu#cca mE vrIqhaya#Sca mEq yavA$Sca mEq mAShA$Sca mEq tilA$Sca mE muqdgASca# mE KaqlvA$Sca mE gOqdhUmA$Sca mE maqsurA$- ( ) -Sca mE priqyaMga#vaScaq mE &Na#vaSca mE SyAqmAkA$Sca mE nIqvArA$Sca mE || 8",
      "citta": {
        "section_count": "(8)",
        "anuvaka": "(A4)",
        "marker": "(viqBu ca# - maqsurAq - Scatu#rdaSa ca)"
      }
    }
  ]
}
