{
  "metadata": {
    "source": "vedanidhi",
    "veda": "samaveda",
    "shakha": "कौथुमशाखा",
    "text_type": "प्रकृति, आरण्यकगानम् - (03030207) काण्डम्",
    "source_id": "03030207",
    "total_texts": 189,
    "accent_percentage_sample": 86.0,
    "downloaded_at": "2025-05-28T23:15:41.621369"
  },
  "texts": [
    {
      "location": [
        "सा",
        "कौ",
        null
      ],
      "vaakya_pk": 37665,
      "vaakya_text": "अथ आरण्यकगानम्।। अर्कपर्व",
      "vaakya_sk": "03030207",
      "permission": false
    },
    {
      "location": [
        "सा",
        "कौ",
        null,
        "07 काण्ड"
      ],
      "vaakya_pk": 37666,
      "vaakya_text": "प्रथमप्रपाठके प्रथमोर्धः",
      "vaakya_sk": "0303020701",
      "permission": false
    },
    {
      "location": [
        "सा",
        "कौ",
        null,
        "07 काण्ड",
        "01 प्रपा"
      ],
      "vaakya_pk": 37667,
      "vaakya_text": "अथ प्रथमः खण्डः",
      "vaakya_sk": "030302070101",
      "permission": false
    },
    {
      "location": [
        "सा",
        "कौ",
        null,
        "07 काण्ड",
        "01 प्रपा",
        "01 अनु",
        "001 पञ्चा"
      ],
      "vaakya_pk": 37668,
      "vaakya_text": "अष्टौ वैरूपाणि (अञ्जो वैरूपम्)।। वैरूपो बृहतीन्द्र इन्द्रसूर्यौ वा।।",
      "vaakya_sk": "030302070101001001",
      "permission": false
    },
    {
      "location": [
        "सा",
        "कौ",
        null,
        "07 काण्ड",
        "01 प्रपा",
        "01 अनु",
        "001 पञ्चा"
      ],
      "vaakya_pk": 37669,
      "vaakya_text": "ओम्।। यद्यावई।। द्रताग़31उवा23। शा234ताम्। हाहाग़31उवा23। ई234डा। शतंभूमी। उताग़31उवा23। सी234यू।। हाहाग़31उवा23। ई234डा।। नत्वावज्रिन्त्सहस्रसू। रियाग़31उवा23।। आ234नू। हाहाग़31उवा23। ई234डा। नजातम। ष्टरोग़3। आउ। वा23। दा234सी। हाहाग़31उवा23।। इट्(स्थि)इडा2345।।",
      "vaakya_sk": "030302070101001002",
      "permission": false
    },
    {
      "location": [
        "सा",
        "कौ",
        null,
        "07 काण्ड",
        "01 प्रपा",
        "01 अनु",
        "002 पञ्चा"
      ],
      "vaakya_pk": 37670,
      "vaakya_text": "ह्रस्वावैरूपम्।।",
      "vaakya_sk": "030302070101002001",
      "permission": false
    },
    {
      "location": [
        "सा",
        "कौ",
        null,
        "07 काण्ड",
        "01 प्रपा",
        "01 अनु",
        "002 पञ्चा"
      ],
      "vaakya_pk": 37671,
      "vaakya_text": "यद्यावइन्द्रतेशतम्। ए। शतंभूमीरुत। स्योवा।। नात्वावज्रिन्। सहस्रसूरियाख़आनूख़।। नाजाख़तमा।। ष्टरो23। दा2ग़सा234 औहोवा।। दिशंविशहस्। अश्वाशिशुमतीग़3। इट्(स्थि)इडा2345।। \t\t\t\t\t      ◌दी-10। प-12। मा-7।। 2 (फे) 2।।",
      "vaakya_sk": "030302070101002002",
      "permission": false
    },
    {
      "location": [
        "सा",
        "कौ",
        null,
        "07 काण्ड",
        "01 प्रपा",
        "01 अनु",
        "003 पञ्चा"
      ],
      "vaakya_pk": 37672,
      "vaakya_text": "पञ्चनिधनं वैरूपम्।।",
      "vaakya_sk": "030302070101003001",
      "permission": false
    },
    {
      "location": [
        "सा",
        "कौ",
        null,
        "07 काण्ड",
        "01 प्रपा",
        "01 अनु",
        "003 पञ्चा"
      ],
      "vaakya_pk": 37673,
      "vaakya_text": "यद्यावइन्द्रतेशतम्। ए। शतंभूमीरुत। स्योवा।। ओवाख़। हख़।(त्रिः)। ओवाढ़ग़3। हाउवा। नत्वावज्रिन्त्सहस्रसूर्याअनु। ओवाख़। हख़।(त्रिः)। ओवाढ़ग़3। हाउवा। नजातमष्टरोदसी।। ओवाख़। हख़।(त्रिः)। ओवाढ़ग़3। हाउवा। दिशंविशहस्।। ओवाख़। हख़।(त्रिः)। ओवाढ़ग़3। हाउवा। अश्वा शिशुमती। ओवाख़। हख़।(त्रिः)। ओवाढ़ग़3। हाउवाग़3।। इट्(स्थि) इडा2345।।",
      "vaakya_sk": "030302070101003002",
      "permission": false
    },
    {
      "location": [
        "सा",
        "कौ",
        null,
        "07 काण्ड",
        "01 प्रपा",
        "01 अनु",
        "004 पञ्चा"
      ],
      "vaakya_pk": 37674,
      "vaakya_text": "षण्णिधनं वैरूपम्।।",
      "vaakya_sk": "030302070101004001",
      "permission": false
    },
    {
      "location": [
        "सा",
        "कौ",
        null,
        "07 काण्ड",
        "01 प्रपा",
        "01 अनु",
        "004 पञ्चा"
      ],
      "vaakya_pk": 37675,
      "vaakya_text": "यद्यावइन्द्रतेशतम्। ए। शतंभूमीरुत। स्योवा।। हाउहाउहाउवा। नत्वावज्रिन्त्सहस्रसूर्याअनु। हाउहाउहाउवा। नजातमष्टरोदसी। हाउहाउ हाउवा। दिशंविशहस्।। हाउहाउहाउवा। अश्वाशिशुमती। हाउहाउहाउवा।। युवतिश्चकुमारिणी। हाउहाउहाउवाग़3।। इट्(स्थि)इडा2345।।",
      "vaakya_sk": "030302070101004002",
      "permission": false
    },
    {
      "location": [
        "सा",
        "कौ",
        null,
        "07 काण्ड",
        "01 प्रपा",
        "01 अनु",
        "005 पञ्चा"
      ],
      "vaakya_pk": 37676,
      "vaakya_text": "सप्त निधनं वैरूपम्।।",
      "vaakya_sk": "030302070101005001",
      "permission": false
    },
    {
      "location": [
        "सा",
        "कौ",
        null,
        "07 काण्ड",
        "01 प्रपा",
        "01 अनु",
        "005 पञ्चा"
      ],
      "vaakya_pk": 37677,
      "vaakya_text": "यद्यावइन्द्रतेशतम्। ए। शतंभूमीरुत। स्योवा।। हाउहाउहाउवा। नत्वा वज्रिन्त्सहस्रसूर्याअनु। हाउहाउहाउवा। नजातमष्टरोदसी। हाउहाउहाउवा। दिशंविशहस्।। हाउहाउहाउवा। अश्वाशिशुमती। हाउहाउहाउवा। सूव। हाउहाउहाउवा। ज्योतिः।। हाउहाउहाउवाग़3।। इट्(स्थि)इडा2345।। \t\t\t\t\t    ◌दी-15। प-18। मा-38।। 5 (बै) 5।।",
      "vaakya_sk": "030302070101005002",
      "permission": false
    },
    {
      "location": [
        "सा",
        "कौ",
        null,
        "07 काण्ड",
        "01 प्रपा",
        "01 अनु",
        "006 पञ्चा"
      ],
      "vaakya_pk": 37678,
      "vaakya_text": "अष्टा निधनं वैरूपम्।।",
      "vaakya_sk": "030302070101006001",
      "permission": false
    },
    {
      "location": [
        "सा",
        "कौ",
        null,
        "07 काण्ड",
        "01 प्रपा",
        "01 अनु",
        "006 पञ्चा"
      ],
      "vaakya_pk": 37679,
      "vaakya_text": "यद्यावइन्द्रतेशतम्। ए। शतंभूमीरुत। स्योवा।। हाउहाउहाउवा। नत्वा वज्रिन्त्सहस्रसूर्याअनु। हाउहाउहाउवा। नजातमष्टरोदसी। हाउहाउहाउवा। दिशंविशहस्।। हाउहाउहाउवा।। अश्वाशिशुमती।। हाउहाउहाउवा।। युवतिश्चकुमारिणी।। हाउहाउहाउवा। सूव। हाउहाउहाउवा। ज्योतिः। हाउहाउहाउवाग़3।। इट्(स्थि)इडा2345।।        ◌दी-17। प-20। मा-31।। 6(ञ) 6।।",
      "vaakya_sk": "030302070101006002",
      "permission": false
    },
    {
      "location": [
        "सा",
        "कौ",
        null,
        "07 काण्ड",
        "01 प्रपा",
        "01 अनु",
        "007 पञ्चा"
      ],
      "vaakya_pk": 37680,
      "vaakya_text": "द्वादश निधनं वैरूपम्।।",
      "vaakya_sk": "030302070101007001",
      "permission": false
    },
    {
      "location": [
        "सा",
        "कौ",
        null,
        "07 काण्ड",
        "01 प्रपा",
        "01 अनु",
        "007 पञ्चा"
      ],
      "vaakya_pk": 37681,
      "vaakya_text": "यद्यावइन्द्रतेशतम्। ए। शतंभूमीरुत। स्योवा।। ओहहाउहाउ। ओहहाउवा। नत्वावज्रिन्त्सहस्रसूर्याअनु। ओहाओहा। ओहाओहा। ओहा ओहाग़3। हाउवा। नजातमष्टरोदसी। ओहहाउहाउ। ओहहाउवा। दिशंविशहस्।। ओहाओहा। ओहाओहा। ओहाओहाग़3। हाउवा। अश्वा शिशुमती।। ओहहाउहाउ। ओहहाउवा। सूवा। ओहाओहा। ओहाओहा। ओहाओहाग़3। हाउवा। ज्योतिः। ओहहाउहाउ। ओहहाउवा। ईडा। ओहा ओहा। ओहाओहा। ओहाओहाग़3। हाउवा। इट्(स्थि)इडा। ओहहाउहाउ। ओहहाउवाग़3। हौग़3। आग़3। ऊग़3। ई2345।।",
      "vaakya_sk": "030302070101007002",
      "permission": false
    },
    {
      "location": [
        "सा",
        "कौ",
        null,
        "07 काण्ड",
        "01 प्रपा",
        "01 अनु",
        "008 पञ्चा"
      ],
      "vaakya_pk": 37682,
      "vaakya_text": "पुष्यं वैरूपम्।।",
      "vaakya_sk": "030302070101008001",
      "permission": false
    },
    {
      "location": [
        "सा",
        "कौ",
        null,
        "07 काण्ड",
        "01 प्रपा",
        "01 अनु",
        "008 पञ्चा"
      ],
      "vaakya_pk": 37683,
      "vaakya_text": "यद्यावइन्द्रतेशतम्। ए। शतंभूमीरुत। स्योवा।। हाओवा।(द्विः)। हुवे। हाओवा। हुवे। हा ग़ओ234वा। नत्वावज्रिन्त्सहस्रसूर्याअनु। हाओवा। (त्रिः)। हुवे। हाओवा।(द्वे-द्विः)। हुवे। हा ग़ओ234वा। नजातमष्टरोदसी। हाओवा।(चतुः)। हुवे। हाओवा।(द्वे-चतुः)।। नाजातमष्टरोदसाइ। ऐहोइ। आ234इही।(त्रीणि-चतुः)।। हाओवा।(पञ्च)। हुवे। हाओवा।(द्वे-पञ्च)। हैहैहैहोवाढ़ग़3। हाउवाग़3।। ऊ2345।। \t\t\t\t             ◌दी-115। प-63। मा-44।। 8 (वीं) 8।।",
      "vaakya_sk": "030302070101008002",
      "permission": false
    },
    {
      "location": [
        "सा",
        "कौ",
        null,
        "07 काण्ड",
        "01 प्रपा",
        "01 अनु",
        "009 पञ्चा"
      ],
      "vaakya_pk": 37684,
      "vaakya_text": "2-1. अन्तरिक्षे द्वे।। द्वयोः प्रजापतिर्बृहतीन्द्रः।।",
      "vaakya_sk": "030302070101009001",
      "permission": false
    },
    {
      "location": [
        "सा",
        "कौ",
        null,
        "07 काण्ड",
        "01 प्रपा",
        "01 अनु",
        "009 पञ्चा"
      ],
      "vaakya_pk": 37685,
      "vaakya_text": "हाउपिबासुता।। स्यरसि। नाः। औहौहोवाख़। इहा। मत्स्वान इन्द्रगोम। ताः। औहौहोवाख़। इहा। आपिर्नोबोधिसधमाद्येवृ। धाइ। औहौ होवाख़। इहा।। अस्माअ। वा। औहौहोवाख़।। इहा। तुताइ। धा2ग़ या234औहोवा।। सुष्टुभस्तुभोऱश्वाशिशुमक्राग़3न्। इट्(स्थि)इडा2345।।",
      "vaakya_sk": "030302070101009002",
      "permission": false
    },
    {
      "location": [
        "सा",
        "कौ",
        null,
        "07 काण्ड",
        "01 प्रपा",
        "01 अनु",
        "010 पञ्चा"
      ],
      "vaakya_pk": 37686,
      "vaakya_text": "2-2.",
      "vaakya_sk": "030302070101010001",
      "permission": false
    },
    {
      "location": [
        "सा",
        "कौ",
        null,
        "07 काण्ड",
        "01 प्रपा",
        "01 अनु",
        "010 पञ्चा"
      ],
      "vaakya_pk": 37687,
      "vaakya_text": "पिबासुता।। स्यरसिनः। मात्स्वा1नाईख़। आ। औग़3होवा हाउवाग़3। ईग़34डा। द्रगोमतः। आपिय़र्नोबोख़। आ। औग़3होवाहाउवाग़3। ईग़34डा। धिसधमाद्येवृधे।। आस्मा1अवाख़। आ। औग़3होवाहाउवाग़3। ईग़34डा। तुताइ।। धा2ग़या234औहोवा।। विष्टुभस्तुभोश्वाशिशु मक्राग़3न्। इट्(स्थि)इडा2345।। \t\t\t\t\t ◌दी-15। प-20। मा-11।। 10 (म) 10।।",
      "vaakya_sk": "030302070101010002",
      "permission": false
    },
    {
      "location": [
        "सा",
        "कौ",
        null,
        "07 काण्ड",
        "01 प्रपा",
        "01 अनु",
        "011 पञ्चा"
      ],
      "vaakya_pk": 37688,
      "vaakya_text": "3-1. अरिष्टे द्वे।। द्वयोः प्रजापतिर्जगती सोमः देवा ब्रह्मणस्पतिर्वा।।",
      "vaakya_sk": "030302070101011001",
      "permission": false
    },
    {
      "location": [
        "सा",
        "कौ",
        null,
        "07 काण्ड",
        "01 प्रपा",
        "01 अनु",
        "011 पञ्चा"
      ],
      "vaakya_pk": 37689,
      "vaakya_text": "हाह। होइया।(द्वे-त्रिः)। पावी। त्रंताइ। वितताग़3म्ब्र। ह्मण ग़स्पा 234ताइ।। प्राभू। गात्रा। णीग़3परियाइ। षिवाइग़श्वा234ता।। आता। प्तता। नूग़3र्नतदा। मोअश्नू234ताइ।। शार्ता। सआइत्। वहन्तः। सम्। तदाशा234ता। हाह। होइया।(द्वे-त्रिः)।। होइडा।(द्विः)। हो2345इ। डा।। \t\t\t\t\t\t\t\t◌दी-26। प-33। मा-22।। 11 (गा) 11।।",
      "vaakya_sk": "030302070101011002",
      "permission": false
    },
    {
      "location": [
        "सा",
        "कौ",
        null,
        "07 काण्ड",
        "01 प्रपा",
        "01 अनु",
        "012 पञ्चा"
      ],
      "vaakya_pk": 37690,
      "vaakya_text": "3-2.",
      "vaakya_sk": "030302070101012001",
      "permission": false
    },
    {
      "location": [
        "सा",
        "कौ",
        null,
        "07 काण्ड",
        "01 प्रपा",
        "01 अनु",
        "012 पञ्चा"
      ],
      "vaakya_pk": 37691,
      "vaakya_text": "हाह। हौग़345।(द्वे-त्रिः)। पावी। त्रंताइ। वितताग़3म्ब्र। ह्मण ग़ स्पा234ताइ।। प्राभू। गात्रा। णीग़3परियाइ। षिवाइग़श्वा234ता।। आता। प्तता। नूग़3र्नतदा। मोअश्नू234ताइ।। शार्ता। सआइत्। वहन्तः। सम्। तदाशा234ता। हाह। हौग़345।।(द्वे-त्रिः)। होइडा।(द्विः)। हो2345इ।। डा।।            \t\t\t\t\t\t ◌दी-14। प-33। मा-16।। 12 (दू) 12।।",
      "vaakya_sk": "030302070101012002",
      "permission": false
    },
    {
      "location": [
        "सा",
        "कौ",
        null,
        "07 काण्ड",
        "01 प्रपा",
        "01 अनु",
        "013 पञ्चा"
      ],
      "vaakya_pk": 37692,
      "vaakya_text": "4-1. अहरीते द्वे।। द्वयोः प्रजापतिर्बृहती इन्द्रः ऋभुर्वा।।",
      "vaakya_sk": "030302070101013001",
      "permission": false
    },
    {
      "location": [
        "सा",
        "कौ",
        null,
        "07 काण्ड",
        "01 प्रपा",
        "01 अनु",
        "013 पञ्चा"
      ],
      "vaakya_pk": 37693,
      "vaakya_text": "हावाभी।। त्वापूर्वपीत। याइ। इहाग़3। हाउवा3। बॄ234हात्। इन्द्रास्तोमाइ। भिरायवा। इहाग़3। हाउवा3। बॄ234हात्। समाइ चीना। सऋभवा। समाख़स्वरान्। इहाग़3। हाउवा3। बॄ234हात्।। रुद्रागृणा। तपूर्वियाम्। इहाग़3। हाउवा3। बॄ234हात्। ए। बृहत्।।",
      "vaakya_sk": "030302070101013002",
      "permission": false
    },
    {
      "location": [
        "सा",
        "कौ",
        null,
        "07 काण्ड",
        "01 प्रपा",
        "01 अनु",
        "014 पञ्चा"
      ],
      "vaakya_pk": 37694,
      "vaakya_text": "4-2.",
      "vaakya_sk": "030302070101014001",
      "permission": false
    },
    {
      "location": [
        "सा",
        "कौ",
        null,
        "07 काण्ड",
        "01 प्रपा",
        "01 अनु",
        "014 पञ्चा"
      ],
      "vaakya_pk": 37695,
      "vaakya_text": "अभीहाउ।। त्वापूर्वपीतयाइ। इह। हाग़31उवा23। सू234वा। इन्द्रस्तोमेभिरायवाः। इह। हाग़31उवा23। सू234वा।। समी। चीना सऋभवस्समस्वरान्। इह। हाग़31उवा23। सू234वा।। रुद्रागृणन्त पूर्वियाम्। इह। हाग़31उवा23। सू234वा।। एग़3। सुवा2345।।",
      "vaakya_sk": "030302070101014002",
      "permission": false
    },
    {
      "location": [
        "सा",
        "कौ",
        null,
        "07 काण्ड",
        "01 प्रपा"
      ],
      "vaakya_pk": 37696,
      "vaakya_text": "अथ द्वितीयः खण्डः",
      "vaakya_sk": "030302070102",
      "permission": false
    },
    {
      "location": [
        "सा",
        "कौ",
        null,
        "07 काण्ड",
        "01 प्रपा",
        "02 अनु",
        "001 पञ्चा"
      ],
      "vaakya_pk": 37697,
      "vaakya_text": "5-1. वरुणस्य देवस्थानम्।। वरुणो बृहती इन्द्रः।।",
      "vaakya_sk": "030302070102001001",
      "permission": false
    },
    {
      "location": [
        "सा",
        "कौ",
        null,
        "07 काण्ड",
        "01 प्रपा",
        "02 अनु",
        "001 पञ्चा"
      ],
      "vaakya_pk": 37698,
      "vaakya_text": "हाउपिबासुता।। स्यरसिनाग़3। होइ।(त्रिः)। हाउहाउहाउवा। सहोनरः। मत्स्वानइन्द्रगोमताग़3। होइ।(त्रिः)। हाउहाउहाउवा। सत्यमोजः।। आपिर्नोबोधिसधमाग़3। होइ।(त्रिः)। हाउहाउहाउवा। स्वर्ज्योतिः।। दियेवृधेग़3। होइ।(त्रिः)। हाउहाउहाउवा।। एस्थादिदम्।(त्रिः)। अस्माअ वन्तुतेधियाग़3। होइ।(त्रिः)। हाउहाउहाउवा।। द्यौरक्रान्भूमिरततन त्समुद्रसमचूकुपत्। इट्(स्थि)इडा2345।। \t\t\t\t\t◌दी-23। प-34। मा-44।। 15 (ढी) 15।।",
      "vaakya_sk": "030302070102001002",
      "permission": false
    },
    {
      "location": [
        "सा",
        "कौ",
        null,
        "07 काण्ड",
        "01 प्रपा",
        "02 अनु",
        "002 पञ्चा"
      ],
      "vaakya_pk": 37699,
      "vaakya_text": "6-1. बृहद्देवस्थानम्।। प्रजापतिर्बृहती मरुतः।।",
      "vaakya_sk": "030302070102002001",
      "permission": false
    },
    {
      "location": [
        "सा",
        "कौ",
        null,
        "07 काण्ड",
        "01 प्रपा",
        "02 अनु",
        "002 पञ्चा"
      ],
      "vaakya_pk": 37700,
      "vaakya_text": "हाउहाउहाउ। बृहात्।(त्रिः)। बॄहत्।(त्रिः)। बृहात्।(त्रिः)। बृहदिन्द्रा यग़3गाया1ताख़।। मरुतोवृत्रग़3हान्ता1माख़म्।। येनज्योतिरजनय न्नॄग़3तावा1र्द्धाख़।। देवन्देवायग़3जागॄ1वी23। हाउहाउहाउ। बृहात्। (त्रिः)। बॄहत्।(त्रिः)। बृहात्।(द्विः)। बृहाग़31उ। वाख़।। ए। बृहत्। (द्वे-त्रिः)।।",
      "vaakya_sk": "030302070102002002",
      "permission": false
    },
    {
      "location": [
        "सा",
        "कौ",
        null,
        "07 काण्ड",
        "01 प्रपा",
        "02 अनु",
        "003 पञ्चा"
      ],
      "vaakya_pk": 37701,
      "vaakya_text": "7-1. ऐरयदैरिणे द्वे।। वरुणो बृहती सोमः।।",
      "vaakya_sk": "030302070102003001",
      "permission": false
    },
    {
      "location": [
        "सा",
        "कौ",
        null,
        "07 काण्ड",
        "01 प्रपा",
        "02 अनु",
        "003 पञ्चा"
      ],
      "vaakya_pk": 37702,
      "vaakya_text": "ऐरायाख़त्।(द्विः)। ऐराया23त्। सुवराग़34। हाहोइ। पुनानस्सोमग़3 धारा1याख़।। अपोवसानोग़3आर्षा1सीख़।। आरत्नधायोनिमृतस्यग़3 साइदा1सीख़।। उत्सोदेवोहिग़3राण्या1याख़।। ऐरायाख़त्।(द्विः)। ऐरा या23त्। सुवराग़34। हाहाग़34। औहोवा।। एग़3। देवादिवाज्योती 2345।। \t\t◌दी-25। प-17। मा-11।। 17 (फ) 17।।",
      "vaakya_sk": "030302070102003002",
      "permission": false
    },
    {
      "location": [
        "सा",
        "कौ",
        null,
        "07 काण्ड",
        "01 प्रपा",
        "02 अनु",
        "004 पञ्चा"
      ],
      "vaakya_pk": 37703,
      "vaakya_text": "8-1. वरुणो गायत्री इन्द्रः।।",
      "vaakya_sk": "030302070102004001",
      "permission": false
    },
    {
      "location": [
        "सा",
        "कौ",
        null,
        "07 काण्ड",
        "01 प्रपा",
        "02 अनु",
        "004 पञ्चा"
      ],
      "vaakya_pk": 37704,
      "vaakya_text": "हावौहोहाउ। अभित्वावार्षाग़3भासुताइ। अभित्वावा। षाभासुताइ। अभित्वावार्षाग़3भासुताइ।। औहोहावौहोख़। सुतसृजामीग़3पीतयाइ। सुतसृजा। मीपीतयाइ। सुतसृजामीग़3पीतयाइ।। हावौहोहाउ। तृपा वियाश्नूग़3हीमदाम्। तृपाविया। श्नूहीमदाम्। तृम्पावियाश्नूग़3हीमदाम्।। औहोहावौहो2। उहुवाग़3हाउ। वाग़3।। हस्।। \t◌दी-34। प-19। मा-13।। 18 (धि) 18।।",
      "vaakya_sk": "030302070102004002",
      "permission": false
    },
    {
      "location": [
        "सा",
        "कौ",
        null,
        "07 काण्ड",
        "01 प्रपा",
        "02 अनु",
        "005 पञ्चा"
      ],
      "vaakya_pk": 37705,
      "vaakya_text": "9-1. आङ्गिरसे द्वे।। अङ्गिरा बृहती सोमः।।",
      "vaakya_sk": "030302070102005001",
      "permission": false
    },
    {
      "location": [
        "सा",
        "कौ",
        null,
        "07 काण्ड",
        "01 प्रपा",
        "02 अनु",
        "005 पञ्चा"
      ],
      "vaakya_pk": 37706,
      "vaakya_text": "हाउहाउहाउ। हौवाग़ओ234वा। हाहाग़31उवाख़। पुनानस्सोम धारया। श्रवोबृहदिहाइडा।। अपोवसानोअर्षसि। श्रवोबृहदिहाइडा।। आरत्न धायोनिमृतस्यसीदसि। श्रवोबृहदिहाइडा।। उत्सोदेवोहिरण्यय। श्रवोबृह दिहाइडा। हाउहाउहाउ। हौवाओ234वा। हाहाग़31उवाख़।। सुवर्जगन्म महस्पृथिव्यादिवमाशकेमवाजिनोयमम्। हस्। इट्(स्थि)इडा2345।।",
      "vaakya_sk": "030302070102005002",
      "permission": false
    },
    {
      "location": [
        "सा",
        "कौ",
        null,
        "07 काण्ड",
        "01 प्रपा",
        "02 अनु",
        "006 पञ्चा"
      ],
      "vaakya_pk": 37707,
      "vaakya_text": "10-1. (तत्रोत्तरम्)",
      "vaakya_sk": "030302070102006001",
      "permission": false
    },
    {
      "location": [
        "सा",
        "कौ",
        null,
        "07 काण्ड",
        "01 प्रपा",
        "02 अनु",
        "006 पञ्चा"
      ],
      "vaakya_pk": 37708,
      "vaakya_text": "औहोवाऔहोवाऔहोग़3वा। तवेदिन्द्रावमंवसु।। त्वंपुष्यसिमध्यमम्।। सत्राविश्वस्यपरमस्यराजसि।। नकिष्ट्वागोषुवृण्वते। औहोवाऔहोवा औहोग़3वा।। सुवर्जगन्मदेवानामवसावयशकेमवाजिनोयमम्। सुवर्जग न्ममहस्पृथिव्यादिवमा। हस्(स्थि)बृहन्नमा2345।। ◌दी-30। प-9। मा-8।। 20 (भै) 20।।",
      "vaakya_sk": "030302070102006002",
      "permission": false
    },
    {
      "location": [
        "सा",
        "कौ",
        null,
        "07 काण्ड",
        "01 प्रपा",
        "02 अनु",
        "007 पञ्चा"
      ],
      "vaakya_pk": 37709,
      "vaakya_text": "10-2. बार्हस्पत्यम्।। बृहस्पतिः बृहती इन्द्रः।।",
      "vaakya_sk": "030302070102007001",
      "permission": false
    },
    {
      "location": [
        "सा",
        "कौ",
        null,
        "07 काण्ड",
        "01 प्रपा",
        "02 अनु",
        "007 पञ्चा"
      ],
      "vaakya_pk": 37710,
      "vaakya_text": "औहोऔहोग़3वा।(त्रिः)। इडा23भिराग़34। औहोवा। तवेदिन्द्रा वमंवसु।। त्वंपुष्यसिमध्यमम्।। सत्राविश्वस्यपरमस्यराजसि।। नकिष्ट्वा गोषुवृण्वते। औहोऔहोग़3वा।(त्रिः)। इडा23भिराग़34। औहोवा।। इडा सुवोबृहन्नमा2345।। \t\t  \t◌दी-31। प-15। मा-8।। 21 (ङै) 21।।",
      "vaakya_sk": "030302070102007002",
      "permission": false
    },
    {
      "location": [
        "सा",
        "कौ",
        null,
        "07 काण्ड",
        "01 प्रपा",
        "02 अनु",
        "008 पञ्चा"
      ],
      "vaakya_pk": 37711,
      "vaakya_text": "11-1. भारद्वाजम्।। भरद्वाजो बृहती इन्द्रः।।",
      "vaakya_sk": "030302070102008001",
      "permission": false
    },
    {
      "location": [
        "सा",
        "कौ",
        null,
        "07 काण्ड",
        "01 प्रपा",
        "02 अनु",
        "008 पञ्चा"
      ],
      "vaakya_pk": 37712,
      "vaakya_text": "हाउहाउहाउ। औहोआत्वासहस्रमाशताम्।। हाउहाउहाउ। युक्तारा1 था23इ। हाउहाउहाउ।",
      "vaakya_sk": "030302070102008002",
      "permission": false
    },
    {
      "location": [
        "सा",
        "कौ",
        null,
        "07 काण्ड",
        "01 प्रपा",
        "02 अनु",
        "009 पञ्चा"
      ],
      "vaakya_pk": 37713,
      "vaakya_text": "12-1. आथर्वणम्।। अथर्वा गायत्री आपः।।",
      "vaakya_sk": "030302070102009001",
      "permission": false
    },
    {
      "location": [
        "सा",
        "कौ",
        null,
        "07 काण्ड",
        "01 प्रपा",
        "02 अनु",
        "009 पञ्चा"
      ],
      "vaakya_pk": 37714,
      "vaakya_text": "उहुवाओहा। औहोवा। शन्नोदेवीः।। उहुवाओहा। औहोवाहाउ। वा। आवत्। अभिष्टा23याग़3इ।। उहुवाओहा। औहोवा। शन्नोभवा।। उहुवा ओहा। औहोवाहाउ। वा। सूव। तुपीता23याग़3इ।। उहुवाओहा। औहोवा। शंयोरभी।। उहुवाओहा। औहोवाहाउ। वा। ज्योति। स्रवन्तू23 नाग़3। उहुवाओहा। औहोवाहाउ। वाग़3।। ई2345।। \t ◌दी-43। प-28। मा-18।। 23 (ड्रै) 23।।",
      "vaakya_sk": "030302070102009002",
      "permission": false
    },
    {
      "location": [
        "सा",
        "कौ",
        null,
        "07 काण्ड",
        "01 प्रपा",
        "02 अनु",
        "010 पञ्चा"
      ],
      "vaakya_pk": 37715,
      "vaakya_text": "13-1. नारद्वसवम्।। नरद्वसुर्बृहती इन्द्रः।।",
      "vaakya_sk": "030302070102010001",
      "permission": false
    },
    {
      "location": [
        "सा",
        "कौ",
        null,
        "07 काण्ड",
        "01 प्रपा",
        "02 अनु",
        "010 पञ्चा"
      ],
      "vaakya_pk": 37716,
      "vaakya_text": "हाउहाउहाउ। औहोइन्द्रज्येष्ठन्नआभराग़3ए।। हाउहाउहाउ। औहोख़। ओख़।",
      "vaakya_sk": "030302070102010002",
      "permission": false
    },
    {
      "location": [
        "सा",
        "कौ",
        null,
        "07 काण्ड",
        "01 प्रपा",
        "02 अनु",
        "011 पञ्चा"
      ],
      "vaakya_pk": 37717,
      "vaakya_text": "14-1. बृहती वामदेव्ये द्वे।। वामदेवो गायत्री इन्द्रः।।",
      "vaakya_sk": "030302070102011001",
      "permission": false
    },
    {
      "location": [
        "सा",
        "कौ",
        null,
        "07 काण्ड",
        "01 प्रपा",
        "02 अनु",
        "011 पञ्चा"
      ],
      "vaakya_pk": 37718,
      "vaakya_text": "हाउहाउहाउ। बृहद्वामम्।(त्रिः)। बृहत्पार्थिवम्।(त्रिः)। बृहदन्तरिक्षम्। (त्रिः)। बृहद्दिवम्।(त्रिः)। बृहद्वामम्।(त्रिः)। कयानश्चित्रग़3आभू1वाख़त्।। ऊतीसदावृग़3धास्सा1खाख़।। कयाशचिष्ठग़3यावा1र्ता23।। हाउहाउ हाउ। बृहद्वामम्।(त्रिः)। बृहत्पार्थिवम्।(त्रिः)। बृहदन्तरिक्षम्।(त्रिः)। बृह द्दिवम्।(त्रिः)। बृहद्वामम्।(द्विः)। बृहद्वामम्। औहोवाहाउ। वा।। ए। बृहद्वामम्। ए। बृहद्भ्योवामम्। ए। वामेभ्योवामम्। ए। वामम्। वामम्। वामम्।।",
      "vaakya_sk": "030302070102011002",
      "permission": false
    },
    {
      "location": [
        "सा",
        "कौ",
        null,
        "07 काण्ड",
        "01 प्रपा",
        "02 अनु",
        "011 पञ्चा"
      ],
      "vaakya_pk": 37719,
      "vaakya_text": "14-2.",
      "vaakya_sk": "030302070102011003",
      "permission": false
    },
    {
      "location": [
        "सा",
        "कौ",
        null,
        "07 काण्ड",
        "01 प्रपा",
        "02 अनु",
        "011 पञ्चा"
      ],
      "vaakya_pk": 37720,
      "vaakya_text": "बृहद्वामम्।(त्रिः)। कयानश्चाइ। त्रय़आ2ग़भू234वात्। ऊताइसदा। वार्द्धस्सा234खा।।",
      "vaakya_sk": "030302070102011004",
      "permission": false
    },
    {
      "location": [
        "सा",
        "कौ",
        null,
        "07 काण्ड",
        "01 प्रपा",
        "02 अनु",
        "012 पञ्चा"
      ],
      "vaakya_pk": 37721,
      "vaakya_text": "15-1. बृहत्साम।। भरद्वाजो बृहती इन्द्रः।।",
      "vaakya_sk": "030302070102012001",
      "permission": false
    },
    {
      "location": [
        "सा",
        "कौ",
        null,
        "07 काण्ड",
        "01 प्रपा",
        "02 अनु",
        "012 पञ्चा"
      ],
      "vaakya_pk": 37722,
      "vaakya_text": "औहोइत्वामिद्धिहवामहाग़3ए।। सातौवाजा। स्याका ग़रा234वा। तुवा ग़34।",
      "vaakya_sk": "030302070102012002",
      "permission": false
    },
    {
      "location": [
        "सा",
        "कौ",
        null,
        "07 काण्ड"
      ],
      "vaakya_pk": 37723,
      "vaakya_text": "अथ प्रथमप्रपाठके द्वितीयोर्धः",
      "vaakya_sk": "0303020702",
      "permission": false
    },
    {
      "location": [
        "सा",
        "कौ",
        null,
        "07 काण्ड",
        "02 प्रपा"
      ],
      "vaakya_pk": 37724,
      "vaakya_text": "अथ तृतीयः खण्डः",
      "vaakya_sk": "030302070201",
      "permission": false
    },
    {
      "location": [
        "सा",
        "कौ",
        null,
        "07 काण्ड",
        "02 प्रपा",
        "01 अनु",
        "001 पञ्चा"
      ],
      "vaakya_pk": 37725,
      "vaakya_text": "16-1. वसिष्ठजमदग्न्यरर्कौ द्वौ।। अगस्त्य जमदग्न्योर्वा वसिष्ठस्त्रिष्टुबिन्द्रः।।",
      "vaakya_sk": "030302070201001001",
      "permission": false
    },
    {
      "location": [
        "सा",
        "कौ",
        null,
        "07 काण्ड",
        "02 प्रपा",
        "01 अनु",
        "001 पञ्चा"
      ],
      "vaakya_pk": 37726,
      "vaakya_text": "इयाग़3होइ।(त्रिः)। इन्द्रन्नरो। नेग़3मधि। ताहवन्ताइ।। यत्पारियाः। युनज। ताइग़धियस्ता।। शूरोनृषा। ताग़3श्रव। सश्चकामाइ।। आगोमताइ। व्रजेभ। जातुवन्ना। इयाग़3होइ।(द्विः)। इयाग़3हो2ग़। या234औहोवा।। ई2345।। \t\t   ◌दी-11। प-20। मा-13।। 1 (फे) 28।।",
      "vaakya_sk": "030302070201001002",
      "permission": false
    },
    {
      "location": [
        "सा",
        "कौ",
        null,
        "07 काण्ड",
        "02 प्रपा",
        "01 अनु",
        "002 पञ्चा"
      ],
      "vaakya_pk": 37727,
      "vaakya_text": "16-2. जमदग्निः त्रिष्टुबिन्द्रः।।",
      "vaakya_sk": "030302070201002001",
      "permission": false
    },
    {
      "location": [
        "सा",
        "कौ",
        null,
        "07 काण्ड",
        "02 प्रपा",
        "01 अनु",
        "002 पञ्चा"
      ],
      "vaakya_pk": 37728,
      "vaakya_text": "ओहोइया।(त्रिः)। इन्द्रन्नरो। नेग़3मधि। ताहवन्ताइ।। यत्पारियाः। युनज। ताइग़धियस्ता।। शूरोनृषा। ताग़3श्रव। सश्चकामाइ।। आगोमताइ। व्रजेभ। जातुवन्ना। ओहोइया।(द्विः)। ओहोग़345या656।। ई2345।। \t\t\t  ◌दी-25। प-19। मा-12।। 2 (भ्रा) 29।।",
      "vaakya_sk": "030302070201002002",
      "permission": false
    },
    {
      "location": [
        "सा",
        "कौ",
        null,
        "07 काण्ड",
        "02 प्रपा",
        "01 अनु",
        "003 पञ्चा"
      ],
      "vaakya_pk": 37729,
      "vaakya_text": "17-1. स्वाशिरामर्कः।। स्वाशिरा गायत्री सोमेन्द्रौ।।",
      "vaakya_sk": "030302070201003001",
      "permission": false
    },
    {
      "location": [
        "सा",
        "कौ",
        null,
        "07 काण्ड",
        "02 प्रपा",
        "01 अनु",
        "003 पञ्चा"
      ],
      "vaakya_pk": 37730,
      "vaakya_text": "अयामायाम्।(त्रिः)। स्वादिष्ठया2ग़। मदाइग़ष्ठा234या।। पवस्वसो 2ग़।",
      "vaakya_sk": "030302070201003002",
      "permission": false
    },
    {
      "location": [
        "सा",
        "कौ",
        null,
        "07 काण्ड",
        "02 प्रपा",
        "01 अनु",
        "004 पञ्चा"
      ],
      "vaakya_pk": 37731,
      "vaakya_text": "18-1. दीर्घतमसोर्कः।। दीर्घतमा जगती सोमः।।",
      "vaakya_sk": "030302070201004001",
      "permission": false
    },
    {
      "location": [
        "सा",
        "कौ",
        null,
        "07 काण्ड",
        "02 प्रपा",
        "01 अनु",
        "004 पञ्चा"
      ],
      "vaakya_pk": 37732,
      "vaakya_text": "हाउहाउहाउ। औहोवाएहियाहाउ। धार्त्ता। दाइवपवतेकृत्विय। रसो रसो। रस।। हाउहाउहाउ। औहोवाएहियाहाउ। दाक्षा। दाइवानामनु मादिय। नृभीर्नृभी। नृभी।। हाउहाउहाउ। औहोवाएहियाहाउ। हारी। सार्जानोअत्योनस। त्वभीस्त्वभी। त्वभी।। हाउहाउहाउ। औहोवा एहियाहाउ। वार्था। पाजासिकृणुषेनदी। षुवाषुवा। षुवा। हाउहाउहाउ। औहोवाएहियाग़3हाउ। वाग़3।। ई2345।। \t\t\t\t\t  ◌दी-53। प-28। मा-37।। 4 (ड्रे) 31।।",
      "vaakya_sk": "030302070201004002",
      "permission": false
    },
    {
      "location": [
        "सा",
        "कौ",
        null,
        "07 काण्ड",
        "02 प्रपा",
        "01 अनु",
        "005 पञ्चा"
      ],
      "vaakya_pk": 37733,
      "vaakya_text": "19-1. मरुतामर्कौ द्वौ।। मरुतो बृहती मरुतः।।",
      "vaakya_sk": "030302070201005001",
      "permission": false
    },
    {
      "location": [
        "सा",
        "कौ",
        null,
        "07 काण्ड",
        "02 प्रपा",
        "01 अनु",
        "005 पञ्चा"
      ],
      "vaakya_pk": 37734,
      "vaakya_text": "हाउहाउहाउ। प्रवइन्द्रायबृहाताइ। हाताइ। हाताइ।। हाउहाउहाउ। मरुतोब्रह्मअर्चाता। चाता। चाता।। हाउहाउहाउ। वृत्रहनतिवृत्रहाशत क्रातू। क्रातू। क्रातू।। हाउहाउहाउ। वज्रेणशतपर्वाणा। र्वाणा। र्वाणा। हाउहाउहाउ। वाग़3।। इट्(स्थि)इडा2345।।",
      "vaakya_sk": "030302070201005002",
      "permission": false
    },
    {
      "location": [
        "सा",
        "कौ",
        null,
        "07 काण्ड",
        "02 प्रपा",
        "01 अनु",
        "006 पञ्चा"
      ],
      "vaakya_pk": 37735,
      "vaakya_text": "19-2. मरुतां संस्तोभः।। मरुतो बृहती सोमः।।",
      "vaakya_sk": "030302070201006001",
      "permission": false
    },
    {
      "location": [
        "सा",
        "कौ",
        null,
        "07 काण्ड",
        "02 प्रपा",
        "01 अनु",
        "006 पञ्चा"
      ],
      "vaakya_pk": 37736,
      "vaakya_text": "हाउहाउहाउ। सन्त्वानोनवुः।(त्रिः)। अनोनवुः।(त्रिः)। मरुतः। (त्रिः)। विश्वस्मात्।(त्रिः)। प्रवइन्द्रायबृहाताइ। हाताइ।(द्विः)।। मरुतोब्रह्म अर्चाता। चाता।(द्विः)।। वृत्रहनतिवृत्रहाशतक्रातू। क्रातू।(द्विः)।। वज्रेण शतपर्वाणा। र्वाणा।(द्विः)।। हाउहाउहाउ। सन्त्वानोनवुः।(त्रिः)। अनोनवुः। (त्रिः)। मरुतः।(त्रिः)। विश्वस्मात्।(द्विः)। वाइश्वस्मा234औहोवा।। ई2345।।",
      "vaakya_sk": "030302070201006002",
      "permission": false
    },
    {
      "location": [
        "सा",
        "कौ",
        null,
        "07 काण्ड",
        "02 प्रपा",
        "01 अनु",
        "007 पञ्चा"
      ],
      "vaakya_pk": 37737,
      "vaakya_text": "20-1. अग्नेरर्कः।। अग्निः गायत्र्यग्निः।।",
      "vaakya_sk": "030302070201007001",
      "permission": false
    },
    {
      "location": [
        "सा",
        "कौ",
        null,
        "07 काण्ड",
        "02 प्रपा",
        "01 अनु",
        "007 पञ्चा"
      ],
      "vaakya_pk": 37738,
      "vaakya_text": "होहोवा। ई। ईया।(त्रीणि-त्रिः)। अग्निर्मूर्द्धादिग़3वाका1कूख़त्।। पतिपृथीविग़3याआ1याख़म्।। अपारेतासिग़3जाइन्वा1तीख़।। होहोवा। ई। ईया।(त्रीणि-द्विः)। होहोवा। ई। ई2ग़। या234। औहोवा।। ए। अग्निर्मूर्द्धाभवद्दिव।। \t\t\t    ◌दी-11। प-25। मा-5।। 7 (ङु) 34।।",
      "vaakya_sk": "030302070201007002",
      "permission": false
    },
    {
      "location": [
        "सा",
        "कौ",
        null,
        "07 काण्ड",
        "02 प्रपा",
        "01 अनु",
        "008 पञ्चा"
      ],
      "vaakya_pk": 37739,
      "vaakya_text": "21-1. प्रजापतेरर्कः।। प्रजापतिरनुष्टुप् द्यावापृथिवी।।",
      "vaakya_sk": "030302070201008001",
      "permission": false
    },
    {
      "location": [
        "सा",
        "कौ",
        null,
        "07 काण्ड",
        "02 प्रपा",
        "01 अनु",
        "008 पञ्चा"
      ],
      "vaakya_pk": 37740,
      "vaakya_text": "होवा। ईया। औ23होआग़3। आयाम्। पूषा2ग़। रयिर्भा234 गा।। सोमा। पुना2ग़। नोअर्षा234ती।। पाती। विश्वा2ग़। स्यभू ग़मा 234ना।। वाया। ख्यद्रो2ग़। दसी ग़ऊ234भाइ। होवा। ईया। औ23 होआग़34। औहोवा।। ई2345।।",
      "vaakya_sk": "030302070201008002",
      "permission": false
    },
    {
      "location": [
        "सा",
        "कौ",
        null,
        "07 काण्ड",
        "02 प्रपा",
        "01 अनु",
        "009 पञ्चा"
      ],
      "vaakya_pk": 37741,
      "vaakya_text": "22-1. इन्द्रस्यार्कौ द्वौ।। इन्द्रस्त्रिष्टुबिन्द्रः।।",
      "vaakya_sk": "030302070201009001",
      "permission": false
    },
    {
      "location": [
        "सा",
        "कौ",
        null,
        "07 काण्ड",
        "02 प्रपा",
        "01 अनु",
        "009 पञ्चा"
      ],
      "vaakya_pk": 37742,
      "vaakya_text": "हावीन्द्रा।। राजा। जगतः। चर्षणीनाम्। नाम्। नाम्। नाओइनम्। (त्रिः)। नाहोइनम्।(त्रिः)। हावौहोहाउ। अधिक्षमा। विश्वरू। पंयदस्या। स्या। स्या। स्याओइनम्।(त्रिः)। स्याहोइनम्।(त्रिः)। औहोहावौहोख़।। ततोददा। तीग़3दाशु। षाइवसूनी। नी। नी। नाओइनम्।(त्रिः)। नाहोइनम्। (त्रिः)। हावौहोहाउ।। चोदद्राधाः। उपस्तु। तंचिदर्वा। र्वा। र्वा। र्वाओइनम्। (त्रिः)। र्वाहोइनम्।(त्रिः)।",
      "vaakya_sk": "030302070201009002",
      "permission": false
    },
    {
      "location": [
        "सा",
        "कौ",
        null,
        "07 काण्ड",
        "02 प्रपा",
        "01 अनु",
        "010 पञ्चा"
      ],
      "vaakya_pk": 37743,
      "vaakya_text": "22-2.",
      "vaakya_sk": "030302070201010001",
      "permission": false
    },
    {
      "location": [
        "सा",
        "कौ",
        null,
        "07 काण्ड",
        "02 प्रपा",
        "01 अनु",
        "010 पञ्चा"
      ],
      "vaakya_pk": 37744,
      "vaakya_text": "इन्द्रोहाउ।। राजा। जगतः। चर्षणीनाम्। नाम्। नाम्। नोवा। (त्रिः)। नोवाहाइ।(त्रिः)। हाओग़3। हाग़3हाउ। अधिक्षमा। विश्वरू। पंयदस्या। स्या। स्या। स्योवा।(त्रिः)। स्योवाहाइ।(त्रिः)। हाओग़3। हाग़3हाउ।। ततोददा। तीग़3दाशु। षाइवसूनी। नी। नी। नोवा।(त्रिः)। नोवाहाइ।(त्रिः)। हाओग़3। हाग़3हाउ।। चोदद्राधाः। उपस्तु। तंचिदर्वा। र्वा। र्वा। र्वोवा।(त्रिः)। र्वोवाहाइ।(त्रिः)। हाओग़3। हाग़3हाउ। वाग़3।। ई2345।।          \t\t\t◌दी-72। प-55। मा-27।। 10 (ञ्रे) 37।।",
      "vaakya_sk": "030302070201010002",
      "permission": false
    },
    {
      "location": [
        "सा",
        "कौ",
        null,
        "07 काण्ड",
        "02 प्रपा",
        "01 अनु",
        "011 पञ्चा"
      ],
      "vaakya_pk": 37745,
      "vaakya_text": "23-1. अर्कशिरः।। अर्को गायत्रीन्द्रः।।",
      "vaakya_sk": "030302070201011001",
      "permission": false
    },
    {
      "location": [
        "सा",
        "कौ",
        null,
        "07 काण्ड",
        "02 प्रपा",
        "01 अनु",
        "011 पञ्चा"
      ],
      "vaakya_pk": 37746,
      "vaakya_text": "हाउयास्या।। इदमारजोयू1जाख़।। तुजेजनेवनासू1वाख़।। आइन्द्रस्याग़345रा656।। तियंबृहत्।।\t\t\t\t\t\t\t      ◌दी-3। प-5। मा-5।। 11 (णु) 38।।",
      "vaakya_sk": "030302070201011002",
      "permission": false
    },
    {
      "location": [
        "सा",
        "कौ",
        null,
        "07 काण्ड",
        "02 प्रपा",
        "01 अनु",
        "012 पञ्चा"
      ],
      "vaakya_pk": 37747,
      "vaakya_text": "1. अर्कग्रीवः।। अर्कौ यजुरर्कः।।",
      "vaakya_sk": "030302070201012001",
      "permission": false
    },
    {
      "location": [
        "सा",
        "कौ",
        null,
        "07 काण्ड",
        "02 प्रपा",
        "01 अनु",
        "012 पञ्चा"
      ],
      "vaakya_pk": 37748,
      "vaakya_text": "पातीख़।(त्रिः)। दिवआ।। पातीख़।(त्रिः)। अन्तरिक्ष। स्या। पातीख़।(त्रिः)। पार्थिव। स्या।। पातीख़।(त्रिः)। अपामोषधी। नाम्।। पातीख़।(त्रिः)। विश्वस्यभूत। स्या। पातीख़। पाती23। पा2ग़। ता 234। औहोवा।। ए। पतिर्दिव। ए। पतिरन्तरिक्षस्य। ए। पति पार्थिवस्य। ए। पतिरपामोषधीनाम्। ए। पतिर्विश्वस्यभूतस्य। ए। सुवर्ज्योती2345।।",
      "vaakya_sk": "030302070201012002",
      "permission": false
    },
    {
      "location": [
        "सा",
        "कौ",
        null,
        "07 काण्ड",
        "02 प्रपा",
        "01 अनु",
        "013 पञ्चा"
      ],
      "vaakya_pk": 37749,
      "vaakya_text": "24-1. वरुणगोतमयोरर्कः।। वरुणगोतमौ त्रिष्टुप् वरुणादित्यौ।।",
      "vaakya_sk": "030302070201013001",
      "permission": false
    },
    {
      "location": [
        "सा",
        "कौ",
        null,
        "07 काण्ड",
        "02 प्रपा",
        "01 अनु",
        "013 पञ्चा"
      ],
      "vaakya_pk": 37750,
      "vaakya_text": "हाउहाउहाउ। आयुश्चक्षुर्ज्योतिः। औहोवा। ईया। उदुत्तमंवरुणपा शमा23स्मात्।। अवाधमंविमध्यमश्रथा23या।। अथादित्यव्रतेवय न्ता23वा।। अनागसोअदितयेसिया23माग़3। हाउहाउहाउ। आयुश्चक्षु र्ज्योतिः। औहोवा। ई2ग़। या234। औहोवा।। ई2345।।",
      "vaakya_sk": "030302070201013002",
      "permission": false
    },
    {
      "location": [
        "सा",
        "कौ",
        null,
        "07 काण्ड",
        "02 प्रपा",
        "01 अनु",
        "014 पञ्चा"
      ],
      "vaakya_pk": 37751,
      "vaakya_text": "25-1. अर्कपुष्पे द्वे।। द्वयोः प्रजापतिस्त्रिष्टुबिन्द्रः।।",
      "vaakya_sk": "030302070201014001",
      "permission": false
    },
    {
      "location": [
        "सा",
        "कौ",
        null,
        "07 काण्ड",
        "02 प्रपा",
        "01 अनु",
        "014 पञ्चा"
      ],
      "vaakya_pk": 37752,
      "vaakya_text": "इय। होइ। इयइयईढ़ग़3या।(त्रीणि-त्रिः)। इन्द्रन्नरो। नेग़3मधि। ताहवन्ताइ।। यत्पारियाः। युनज। ताइग़धियस्ता।। शूरोनृषा। ताग़3श्रव। सश्चकामाइ।। आगोमताइ। व्रजेभ। जातुवन्ना। इय। होइ। इयइय ईढ़ग़3या।(त्रीणि-द्विः)। इय। होइ। इयइय। ई2ग़। या234। औहोवा।। ई2345।।",
      "vaakya_sk": "030302070201014002",
      "permission": false
    },
    {
      "location": [
        "सा",
        "कौ",
        null,
        "07 काण्ड",
        "02 प्रपा",
        "01 अनु",
        "015 पञ्चा"
      ],
      "vaakya_pk": 37753,
      "vaakya_text": "25-2.",
      "vaakya_sk": "030302070201015001",
      "permission": false
    },
    {
      "location": [
        "सा",
        "कौ",
        null,
        "07 काण्ड",
        "02 प्रपा",
        "01 अनु",
        "015 पञ्चा"
      ],
      "vaakya_pk": 37754,
      "vaakya_text": "उव। होइ। उवउवऊढ़ग़3वा।(त्रीणि-त्रिः)। इन्द्रन्नरो। नेग़3मधि। ताहवन्ताइ।। यत्पारियाः। युनज। ताइग़धियस्ता।। शूरोनृषा। ताग़3श्रव। सश्चकामाइ।। आगोमताइ। व्रजेभ। जातुवन्ना। उव। होइ। उवउव ऊढ़ग़3वा।(त्रीणि-द्विः)। उव। होइ। उवउव। ऊ2ग़। वा234। औहोवा।। ई2345।।",
      "vaakya_sk": "030302070201015002",
      "permission": false
    },
    {
      "location": [
        "सा",
        "कौ",
        null,
        "07 काण्ड",
        "02 प्रपा"
      ],
      "vaakya_pk": 37755,
      "vaakya_text": "अथ चतुर्थः खण्डः",
      "vaakya_sk": "030302070202",
      "permission": false
    },
    {
      "location": [
        "सा",
        "कौ",
        null,
        "07 काण्ड",
        "02 प्रपा",
        "02 अनु",
        "001 पञ्चा"
      ],
      "vaakya_pk": 37756,
      "vaakya_text": "26-1. ज्येष्ठसाम आज्यदोहम्।। अग्निर्वैश्वानरस्त्रिष्टुबग्निर्वैश्वानरः।।",
      "vaakya_sk": "030302070202001001",
      "permission": false
    },
    {
      "location": [
        "सा",
        "कौ",
        null,
        "07 काण्ड",
        "02 प्रपा",
        "02 अनु",
        "001 पञ्चा"
      ],
      "vaakya_pk": 37757,
      "vaakya_text": "हाउहाउहाउ। आज्यदोहम्।(त्रिः)। मूर्द्धानन्दाइ। वाग़3अर। तिंपृ थिव्या।। वैश्वानराम्। ऋतआ। जातमग्नीम्।। कविसम्रा। जाग़3मति। थिंजनानाम्।। आसन्नपा। त्राग़3ञ्जन। यन्तदेवा। हाउहाउहाउ। आज्यदोहम्।(द्विः)। आज्यदो5हाउ। वा।। ए। आज्यदोहम्।(द्वे-द्विः)। ए। आज्यदोहा2345म्।। \t\t\t\t          ◌दी-32। प-27। मा-23।। 16 (छि) 43।।",
      "vaakya_sk": "030302070202001002",
      "permission": false
    },
    {
      "location": [
        "सा",
        "कौ",
        null,
        "07 काण्ड",
        "02 प्रपा",
        "02 अनु",
        "002 पञ्चा"
      ],
      "vaakya_pk": 37758,
      "vaakya_text": "26-2. ईनिधनमाज्यदोहम्।।",
      "vaakya_sk": "030302070202002001",
      "permission": false
    },
    {
      "location": [
        "सा",
        "कौ",
        null,
        "07 काण्ड",
        "02 प्रपा",
        "02 अनु",
        "002 पञ्चा"
      ],
      "vaakya_pk": 37759,
      "vaakya_text": "हाउहाउहाउ। हिम्(स्थि)चिदोहम्। चिदोहम्। चिदोहम्। मूर्द्धा नन्दाइ। वाग़3अर। तिंपृथिव्या।। वैश्वानराम्। ऋतआ। जातमग्नीम्।। कविसम्रा। जाग़3मति। थिंजनानाम्।। आसन्नपा। त्राग़3ञ्जन। यन्तदेवा। हाउहाउहाउ। हिम्(स्थि)चिदोहम्। चिदोहम्। चिदोढ़ग़3हाउ। वाग़3।। ई2345।।",
      "vaakya_sk": "030302070202002002",
      "permission": false
    },
    {
      "location": [
        "सा",
        "कौ",
        null,
        "07 काण्ड",
        "02 प्रपा",
        "02 अनु",
        "003 पञ्चा"
      ],
      "vaakya_pk": 37760,
      "vaakya_text": "26-3. ऋतनिधनमाज्यदोहम्।।",
      "vaakya_sk": "030302070202003001",
      "permission": false
    },
    {
      "location": [
        "सा",
        "कौ",
        null,
        "07 काण्ड",
        "02 प्रपा",
        "02 अनु",
        "003 पञ्चा"
      ],
      "vaakya_pk": 37761,
      "vaakya_text": "हाउहाउहाउ। च्योहम्।(त्रिः)। मूर्द्धानन्दाइ। वाग़3अर। तिंपृ थिव्या।। वैश्वानराम्। ऋतआ। जातमग्नीम्।। कविसम्रा। जाग़3मति। थिंजनानाम्।। आसन्नपा। त्राग़3ञ्जन। यन्तदेवा। हाउहाउहाउ। च्योहम्।(द्विः)। च्योढ़ग़3हाउ। वाग़3।। एग़3। ऋतम्।।",
      "vaakya_sk": "030302070202003002",
      "permission": false
    },
    {
      "location": [
        "सा",
        "कौ",
        null,
        "07 काण्ड",
        "02 प्रपा",
        "02 अनु",
        "004 पञ्चा"
      ],
      "vaakya_pk": 37762,
      "vaakya_text": "27-1. रुद्रस्य त्रय ऋषभाः। तत्रेदं प्रथमं रैवतऋषभः।। रुद्रो गायत्री प्रजापतिः।।",
      "vaakya_sk": "030302070202004001",
      "permission": false
    },
    {
      "location": [
        "सा",
        "कौ",
        null,
        "07 काण्ड",
        "02 प्रपा",
        "02 अनु",
        "004 पञ्चा"
      ],
      "vaakya_pk": 37763,
      "vaakya_text": "सुरूपकृत्नुमूतये।(त्रिः)। सुदुघामिवगोदुहे। जुहूमसाइ।। द्याविद्यवाइ।। (द्विः)। द्याविद्यवाग़31उ। वा23।। उम्।(त्रिः)।। \t\t\t\t\t   ◌दी-15। प-12। मा-7।। 19 (फे) 46।।",
      "vaakya_sk": "030302070202004002",
      "permission": false
    },
    {
      "location": [
        "सा",
        "कौ",
        null,
        "07 काण्ड",
        "02 प्रपा",
        "02 अनु",
        "005 पञ्चा"
      ],
      "vaakya_pk": 37764,
      "vaakya_text": "28-1. वैराजऋषभमिदं द्वितीयम्।। रुद्रो विराडिन्द्रः।।",
      "vaakya_sk": "030302070202005001",
      "permission": false
    },
    {
      "location": [
        "सा",
        "कौ",
        null,
        "07 काण्ड",
        "02 प्रपा",
        "02 अनु",
        "005 पञ्चा"
      ],
      "vaakya_pk": 37765,
      "vaakya_text": "हाउहाउहाउ। आइही।(त्रिः)। आइ।(त्रिः)। इयाहाउ।(त्रिः)। पिबासोमाम्। इन्द्र। मन्दतुत्त्वा।।",
      "vaakya_sk": "030302070202005002",
      "permission": false
    },
    {
      "location": [
        "सा",
        "कौ",
        null,
        "07 काण्ड",
        "02 प्रपा",
        "02 अनु",
        "006 पञ्चा"
      ],
      "vaakya_pk": 37766,
      "vaakya_text": "29-1. शाक्वरऋषभमिति तृतीयम्।। रुद्रः पङ्क्तिरिन्द्रः।।",
      "vaakya_sk": "030302070202006001",
      "permission": false
    },
    {
      "location": [
        "सा",
        "कौ",
        null,
        "07 काण्ड",
        "02 प्रपा",
        "02 अनु",
        "006 पञ्चा"
      ],
      "vaakya_pk": 37767,
      "vaakya_text": "ओग़31म्।(त्रिः)। स्वादोरेइत्थाएविषूएवतआ। शंयो। शंयो।। मधोरेपिबाएन्तिगोएरियआ। हवि।(द्विः)। याआएन्द्रेणाएसयाएवरिया। सुव।।(द्विः)। वृष्णाएमदाएन्तिशोएभथाआ। ज्योति।।(द्विः)। वस्वीरेअनू एस्वराएजियमा। ओग़31म्।(द्विः)। ओग़31234। वा।। इट्(स्थि) इडा2345।। \t\t\t\t\t\t ◌दी-38। प-21। मा-32।। 21 (टा) 48।।",
      "vaakya_sk": "030302070202006002",
      "permission": false
    },
    {
      "location": [
        "सा",
        "कौ",
        null,
        "07 काण्ड",
        "02 प्रपा",
        "02 अनु",
        "007 पञ्चा"
      ],
      "vaakya_pk": 37768,
      "vaakya_text": "अतीषङ्गानि त्रीणि, इन्द्रस्य त्रयोतीङ्गाः,",
      "vaakya_sk": "030302070202007001",
      "permission": false
    },
    {
      "location": [
        "सा",
        "कौ",
        null,
        "07 काण्ड",
        "02 प्रपा",
        "02 अनु",
        "008 पञ्चा"
      ],
      "vaakya_pk": 37769,
      "vaakya_text": "30-1. अथापरं रौद्रः रुद्रः।। इन्द्रः अनुष्टुप्, गायत्री सोमः।।",
      "vaakya_sk": "030302070202008001",
      "permission": false
    },
    {
      "location": [
        "सा",
        "कौ",
        null,
        "07 काण्ड",
        "02 प्रपा",
        "02 अनु",
        "008 पञ्चा"
      ],
      "vaakya_pk": 37770,
      "vaakya_text": "एपुरोजिती।। वोअन्धसस्सुतायमादयाख़इत्नवाइ। इडा।। ऊच्चा।। तेजातमाख़न्धसा। अथा।। दाइवी।। सद्भूमियाख़ददाइ। अथा।। ऊग्रम्।। शर्ममहाख़इश्रवा। अथा। अपश्वानश्नथा1इष्टाग़3ना।। सखायोदीर्घजा 23होइ।। ह्वायमाग़31उवा23।। इट्(स्थि)इडा2345।। \t\t\t\t\t◌दी-12। प-16। मा-13।। 22 (चि) 49।।",
      "vaakya_sk": "030302070202008002",
      "permission": false
    },
    {
      "location": [
        "सा",
        "कौ",
        null,
        "07 काण्ड",
        "02 प्रपा",
        "02 अनु",
        "009 पञ्चा"
      ],
      "vaakya_pk": 37771,
      "vaakya_text": "31-1. वासवः।। इन्द्रः त्रिष्टुप्गायत्री सोमश्येनौ।।",
      "vaakya_sk": "030302070202009001",
      "permission": false
    },
    {
      "location": [
        "सा",
        "कौ",
        null,
        "07 काण्ड",
        "02 प्रपा",
        "02 अनु",
        "009 पञ्चा"
      ],
      "vaakya_pk": 37772,
      "vaakya_text": "एआसा।। जिवक्वारथ्येयथाख़जाउ। इडा।। आसा।। व्यशुर्म दाख़या। अथा।। धाया।। मनोताप्रथमामनाख़इषा। इडा।। आप्सू।। दक्षो गिराख़इष्ठा। अथा।। दाशा।। स्वसारोअधिसानोख़अव्याइ। इडा।। श्याइनो।। नयोनिमाख़सदात्। अथा।। मार्जा।। तिवह्निसदनेषुवा2 च्छाग़31उ। वा23।। इट्(स्थि)इडा2345।।",
      "vaakya_sk": "030302070202009002",
      "permission": false
    },
    {
      "location": [
        "सा",
        "कौ",
        null,
        "07 काण्ड",
        "02 प्रपा",
        "02 अनु",
        "010 पञ्चा"
      ],
      "vaakya_pk": 37773,
      "vaakya_text": "32-1. पार्जन्यो वैश्वदेवो वा।। इन्द्रः अनुष्टुप्गायत्री सोमेन्द्रौ।।",
      "vaakya_sk": "030302070202010001",
      "permission": false
    },
    {
      "location": [
        "सा",
        "कौ",
        null,
        "07 काण्ड",
        "02 प्रपा",
        "02 अनु",
        "010 पञ्चा"
      ],
      "vaakya_pk": 37774,
      "vaakya_text": "एआभी। नवन्तआख़। द्रुहआग़31उवाख़। तरत्समन्दीधावति। प्रायम्। इन्द्रस्यकाख़। मियमाग़31उवाख़। धारासुतस्यान्धस। वात्सम्। नपूर्वआख़। युनियाग़31उवाख़। तरत्समन्दीधावति। जातम्। रिहन्तिमाख़। तरआग़31उवा23। इट्(स्थि)इडा2345।।",
      "vaakya_sk": "030302070202010002",
      "permission": false
    },
    {
      "location": [
        "सा",
        "कौ",
        null,
        "07 काण्ड",
        "02 प्रपा",
        "02 अनु",
        "011 पञ्चा"
      ],
      "vaakya_pk": 37775,
      "vaakya_text": "33-1. प्राजापत्याश्चत्वारः, पदस्तोभाः, अष्टेडपदस्तोभः।। प्रजापति जगती सोमः।।",
      "vaakya_sk": "030302070202011001",
      "permission": false
    },
    {
      "location": [
        "सा",
        "कौ",
        null,
        "07 काण्ड",
        "02 प्रपा",
        "02 अनु",
        "011 पञ्चा"
      ],
      "vaakya_pk": 37776,
      "vaakya_text": "हाह। हौवाग़ओ234वा।(द्वे-त्रिः)। ए। औहौहोवाहाउ। वा। ईडा। धर्त्तादिवपवतेकृत्व्योरस। ईडा।।",
      "vaakya_sk": "030302070202011002",
      "permission": false
    },
    {
      "location": [
        "सा",
        "कौ",
        null,
        "07 काण्ड",
        "02 प्रपा",
        "02 अनु",
        "012 पञ्चा"
      ],
      "vaakya_pk": 37777,
      "vaakya_text": "33-2. षडिडपदस्तोभः गोतमः।।",
      "vaakya_sk": "030302070202012001",
      "permission": false
    },
    {
      "location": [
        "सा",
        "कौ",
        null,
        "07 काण्ड",
        "02 प्रपा",
        "02 अनु",
        "012 पञ्चा"
      ],
      "vaakya_pk": 37778,
      "vaakya_text": "हाउहाउहाउ। हौवाग़ओ234वा। ए। औहौहोवाहाउ। वा। धर्त्ता दिवपवा। ईडा। तेकृत्व्योरस।। ईडा।। दक्षोदेवानामनुमाद्योनृभि। ईडा। हरिस्सृजानआ। ईडा। त्योनसत्वभि।। ईडा। वृथापाजासिकृणुषेनदी षुवा1। हाउहाउहाउ। हौवाग़ओ234वा। ए। औहौहोवाहाउ। वा।। ईडा।।",
      "vaakya_sk": "030302070202012002",
      "permission": false
    },
    {
      "location": [
        "सा",
        "कौ",
        null,
        "07 काण्ड",
        "02 प्रपा",
        "02 अनु",
        "013 पञ्चा"
      ],
      "vaakya_pk": 37779,
      "vaakya_text": "33-3. चतुरिडपदस्तोभः। विश्वामित्रः।।",
      "vaakya_sk": "030302070202013001",
      "permission": false
    },
    {
      "location": [
        "सा",
        "कौ",
        null,
        "07 काण्ड",
        "02 प्रपा",
        "02 अनु",
        "014 पञ्चा"
      ],
      "vaakya_pk": 37780,
      "vaakya_text": "औहौहोवाख़। ओवाख़। ए। औहौहोवाहाउ। वा। धर्त्तादिवपवा। ईडा। तेकृत्व्योरस।। दक्षोदेवानामा। ईडा। नुमाद्योनृभि।। हरिस्सृजा नआ। ईडा। त्योनसत्वभि।। वृथापाजासिकॄ। ईडा। औहौहोवाख़। ओवाख़। ए। औहौहोवाहाउ। वा।। णुषेनदीषुवा1।।",
      "vaakya_sk": "030302070202014001",
      "permission": false
    },
    {
      "location": [
        "सा",
        "कौ",
        null,
        "07 काण्ड",
        "02 प्रपा",
        "02 अनु",
        "015 पञ्चा"
      ],
      "vaakya_pk": 37781,
      "vaakya_text": "33-4. द्विरिडपदस्तोभः। इन्द्राग्नी वा।।",
      "vaakya_sk": "030302070202015001",
      "permission": false
    },
    {
      "location": [
        "सा",
        "कौ",
        null,
        "07 काण्ड",
        "02 प्रपा",
        "02 अनु",
        "015 पञ्चा"
      ],
      "vaakya_pk": 37782,
      "vaakya_text": "आ ग़औहोवाहाइ। ए। औहौहोवाहाउ। वा। धर्त्ता। दीख़। वप। वा। तेकृत्व्य।। रस। दक्षोदेवानामनुमाद्योनृभि। ईडा।। हरि। सा। जानोअ। त्योन।। सत्वभि। वृथापाजासिकृणुषेनदीषुवा1। आ ग़औहोवाहाइ। ए। औहौहोवाहाउ। वा।। ईडा।।",
      "vaakya_sk": "030302070202015002",
      "permission": false
    },
    {
      "location": [
        "सा",
        "कौ",
        null,
        "07 काण्ड"
      ],
      "vaakya_pk": 37783,
      "vaakya_text": "अथ द्वितीयप्रपाठके प्रथमोर्धः",
      "vaakya_sk": "0303020703",
      "permission": false
    },
    {
      "location": [
        "सा",
        "कौ",
        null,
        "07 काण्ड",
        "03 प्रपा"
      ],
      "vaakya_pk": 37784,
      "vaakya_text": "अथ पञ्चमः खण्डः",
      "vaakya_sk": "030302070301",
      "permission": false
    },
    {
      "location": [
        "सा",
        "कौ",
        null,
        "07 काण्ड",
        "03 प्रपा",
        "01 अनु",
        "001 पञ्चा"
      ],
      "vaakya_pk": 37785,
      "vaakya_text": "34-1. दशसंसर्पाणि, सर्पसामानि वा।। अग्निर्जगतीन्द्रः।।",
      "vaakya_sk": "030302070301001001",
      "permission": false
    },
    {
      "location": [
        "सा",
        "कौ",
        null,
        "07 काण्ड",
        "03 प्रपा",
        "01 अनु",
        "001 पञ्चा"
      ],
      "vaakya_pk": 37786,
      "vaakya_text": "अभाइमाहे।(त्रिः)। चर्षणीधृतंमघवानग़3मूक्था1याख़म्।। इन्द्रंगिरो बृहतीरभ्यग़3नूषा1ताख़।। वावृधानंपुरुहूतसुग़3वार्क्ता1इभीख़।। अम र्त्यंजरमाणंदिग़3वाइदा1इवेख़। अभाइमाहे।(द्विः)।",
      "vaakya_sk": "030302070301001002",
      "permission": false
    },
    {
      "location": [
        "सा",
        "कौ",
        null,
        "07 काण्ड",
        "03 प्रपा",
        "01 अनु",
        "002 पञ्चा"
      ],
      "vaakya_pk": 37787,
      "vaakya_text": "34-2. प्रसर्पम्।। पृथिवी जगतीन्द्रः।।",
      "vaakya_sk": "030302070301002001",
      "permission": false
    },
    {
      "location": [
        "सा",
        "कौ",
        null,
        "07 काण्ड",
        "03 प्रपा",
        "01 अनु",
        "002 पञ्चा"
      ],
      "vaakya_pk": 37788,
      "vaakya_text": "अभिप्रमहिग़3राइमाहे।(त्रिः)। चर्षणीधृतंमघवानग़3मूक्था1याख़म्।। इन्द्रगिरोबृहतीरभ्यग़3नूषा1ताख़।। वावृधानंपुरुहूतसुग़3वार्क्ता1इभीख़।। अमर्त्यंजरमाणंदिग़3वाइदा1इवेख़। अभिप्रमहिग़3राइमाहे। (द्विः)। अभिप्रमहिग़3रा23इ। मा2ग़। हा234। औहोवा।। प्रसर्पसुवा 2345।। \t ◌दी-10। प-14। मा-12।। 2 (भा) 57।।",
      "vaakya_sk": "030302070301002002",
      "permission": false
    },
    {
      "location": [
        "सा",
        "कौ",
        null,
        "07 काण्ड",
        "03 प्रपा",
        "01 अनु",
        "003 पञ्चा"
      ],
      "vaakya_pk": 37789,
      "vaakya_text": "34-3. उत्सर्पम्।। वायुर्जगती सोमः।।",
      "vaakya_sk": "030302070301003001",
      "permission": false
    },
    {
      "location": [
        "सा",
        "कौ",
        null,
        "07 काण्ड",
        "03 प्रपा",
        "01 अनु",
        "003 पञ्चा"
      ],
      "vaakya_pk": 37790,
      "vaakya_text": "हाउहाउहाउवा। चर्षणीधृतंमघवानमुक्थ्यम्।। हाउहाउहाउवा। इन्द्रं गिरोबृहतीरभ्यनूषत।। हाउहाउहाउवा। वावृधानम्पुरुहूतसुवृक्तिभिः।। हाउहाउहाउवा। अमर्त्यंजरमाणन्दिवेदिवे। हाउहाउहाउवा।। उत्सर्पसुवा 2345।। \t\t  ◌दी-11। प-10। मा-18।। 3 (ङै) 58।।",
      "vaakya_sk": "030302070301003002",
      "permission": false
    },
    {
      "location": [
        "सा",
        "कौ",
        null,
        "07 काण्ड",
        "03 प्रपा",
        "01 अनु",
        "004 पञ्चा"
      ],
      "vaakya_pk": 37791,
      "vaakya_text": "35-1. अन्तरिक्षस्य सर्पम्।। अन्तरिक्षौ बृहतीन्द्रः।।",
      "vaakya_sk": "030302070301004001",
      "permission": false
    },
    {
      "location": [
        "सा",
        "कौ",
        null,
        "07 काण्ड",
        "03 प्रपा",
        "01 अनु",
        "004 पञ्चा"
      ],
      "vaakya_pk": 37792,
      "vaakya_text": "हाउहाउहाउवा। सुवस्ससर्पन्त। तवेदिन्द्रावमंवसु।। हाउहाउ हाउवा। सुवस्ससर्पन्त। त्वंपुष्यसिमध्यमम्।। हाउहाउहाउवा। सुव स्ससर्पन्त। सत्राविश्वस्यपरमस्यराजसि।। हाउहाउहाउवा। सुवस्स सर्पन्त। नकिष्ट्वागोषुवृण्वते। हाउहाउहाउवा।। सुवस्ससर्पन्त। ए। सर्पतप्रसर्पतसुवर्गमेमतेवयम्।। \t\t\t\t  ◌दी-10। प-16। मा-22।। 4 (पा) 59।।",
      "vaakya_sk": "030302070301004002",
      "permission": false
    },
    {
      "location": [
        "सा",
        "कौ",
        null,
        "07 काण्ड",
        "03 प्रपा",
        "01 अनु",
        "005 पञ्चा"
      ],
      "vaakya_pk": 37793,
      "vaakya_text": "35-2. आदित्यस्य च सर्पम्।। आदित्यो बृहतीन्द्रः।।",
      "vaakya_sk": "030302070301005001",
      "permission": false
    },
    {
      "location": [
        "सा",
        "कौ",
        null,
        "07 काण्ड",
        "03 प्रपा",
        "01 अनु",
        "005 पञ्चा"
      ],
      "vaakya_pk": 37794,
      "vaakya_text": "सुवस्ससार्पससर्पाख़।(द्विः)। सुवस्ससार्पसम्। सा2ग़। पा234। औहोवा। तवेदिन्द्रावमंवसु।। त्वंपुष्यसिमध्यमम्।। सत्राविश्वस्यपरमस्य राजसि।। नकिष्ट्वागोषुवृण्वते। सुवस्ससार्पससर्पाख़।(द्विः)। सुवस्स सार्पसम्। सा2ग़। पा234। औहोवा।। एग़3। सुवर्गमेमा2345।। \t\t\t\t\t    ◌दी-12। प-18। मा-3।। 5 (जि) 60।।",
      "vaakya_sk": "030302070301005002",
      "permission": false
    },
    {
      "location": [
        "सा",
        "कौ",
        null,
        "07 काण्ड",
        "03 प्रपा",
        "01 अनु",
        "006 पञ्चा"
      ],
      "vaakya_pk": 37795,
      "vaakya_text": "36-1. दिवश्च सर्पम्।। द्यौर्जगती सूर्यः।।",
      "vaakya_sk": "030302070301006001",
      "permission": false
    },
    {
      "location": [
        "सा",
        "कौ",
        null,
        "07 काण्ड",
        "03 प्रपा",
        "01 अनु",
        "006 पञ्चा"
      ],
      "vaakya_pk": 37796,
      "vaakya_text": "सृपायप्रसृ। पा। इहा। ईढ़ग़3या।(चत्वारि-त्रिः)। अभिप्रियाणिपवतेच ग़3नोहा1इताख़।। नामानियह्वोअधियेषुग़3वार्द्धा1ताख़इ।। आसूर्यस्य बृहतोबृग़3हाना1धीख़।। रथंविष्वंचमरुहद्विग़3चाक्षा1णाख़। सृपायप्रसृ। पा। इहा। ईढ़ग़3या।(चत्वारि-द्विः)। सृपायप्रसृ। पा। इहा। ई2ग़। या234। औहोवा।। ए। सृपायप्रसृपाय।(द्वे-द्विः)। ए। सृपायप्रसृपाया 2345।।",
      "vaakya_sk": "030302070301006002",
      "permission": false
    },
    {
      "location": [
        "सा",
        "कौ",
        null,
        "07 काण्ड",
        "03 प्रपा",
        "01 अनु",
        "007 पञ्चा"
      ],
      "vaakya_pk": 37797,
      "vaakya_text": "37-1. अपां सर्पसाम।। आपः त्रिष्टुप्सोमः लिंगोक्ता वा।।",
      "vaakya_sk": "030302070301007001",
      "permission": false
    },
    {
      "location": [
        "सा",
        "कौ",
        null,
        "07 काण्ड",
        "03 प्रपा",
        "01 अनु",
        "007 पञ्चा"
      ],
      "vaakya_pk": 37798,
      "vaakya_text": "सृपायप्रसृ। पा। ओहा। ईढ़ग़3या।(चत्वारि-त्रिः)। त्वयावयंपवमाने नसोमा।। भरेकृतंविचिनुयामशाश्वात्।। तन्नोमित्रोवरुणोमामहान्ताम्।। अदितिस्सिन्धुपृथिवीउताद्यौ। सृपायप्रसृ। पा। ओहा।। ईढ़ग़3या। (चत्वारि-द्विः)। सृपायप्रसृ। पा। ओहा। ई2ग़। या234। औहोवा।। ए। सुवः। ए। सुवः। ए। सुवा2345।।\t     ◌दी-27। प-36। मा-7।। 7 (चे) 62।।",
      "vaakya_sk": "030302070301007002",
      "permission": false
    },
    {
      "location": [
        "सा",
        "कौ",
        null,
        "07 काण्ड",
        "03 प्रपा",
        "01 अनु",
        "008 पञ्चा"
      ],
      "vaakya_pk": 37799,
      "vaakya_text": "37-2. समुद्रस्य सर्पसाम।। समुद्रस्रिदीष्टुप्सोमः लिंगोक्ता वा।।",
      "vaakya_sk": "030302070301008001",
      "permission": false
    },
    {
      "location": [
        "सा",
        "कौ",
        null,
        "07 काण्ड",
        "03 प्रपा",
        "01 अनु",
        "008 पञ्चा"
      ],
      "vaakya_pk": 37800,
      "vaakya_text": "सृपायप्रसृ। पा। ओहा।(त्रीणि-त्रिः)। त्वयावयंपवमानेनसोमा।। भरेकृतंविचिनुयामशाश्वात्।। तन्नोमित्रोवरुणोमामहान्ताम्।। अदिति स्सिन्धुपृथिवीउताद्यौ। सृपायप्रसृ। पा। ओहा।(त्रीणि-द्विः)। सृपायप्रसृ। पा। ओ2ग़। हा234। औहोवा। सुवः। ए। सुवः। ए। सुवः। ए2345।।",
      "vaakya_sk": "030302070301008002",
      "permission": false
    },
    {
      "location": [
        "सा",
        "कौ",
        null,
        "07 काण्ड",
        "03 प्रपा",
        "01 अनु",
        "009 पञ्चा"
      ],
      "vaakya_pk": 37801,
      "vaakya_text": "38-1. माण्डवे द्वे।। द्वयोः मण्डुः पङ्क्तिरिन्द्रः।।",
      "vaakya_sk": "030302070301009001",
      "permission": false
    },
    {
      "location": [
        "सा",
        "कौ",
        null,
        "07 काण्ड",
        "03 प्रपा",
        "01 अनु",
        "009 पञ्चा"
      ],
      "vaakya_pk": 37802,
      "vaakya_text": "स्वादोरित्थाविषूवताएहाउ।। मधोपिबन्तिगौरियाएहाउ। याइन्द्रेण सयावराएहाउ।। वृष्णामदन्तिशोभथाएहाउ।। वस्वीरनुस्वराजियामेढ़ग़3 हाउ। वा। ए। दिशप्रदिशक। पा2ग़। ता234। औहोवा।। ए। राजं गमेमस्वराजंगमेमा2345।।",
      "vaakya_sk": "030302070301009002",
      "permission": false
    },
    {
      "location": [
        "सा",
        "कौ",
        null,
        "07 काण्ड",
        "03 प्रपा",
        "01 अनु",
        "010 पञ्चा"
      ],
      "vaakya_pk": 37803,
      "vaakya_text": "38-2.",
      "vaakya_sk": "030302070301010001",
      "permission": false
    },
    {
      "location": [
        "सा",
        "कौ",
        null,
        "07 काण्ड",
        "03 प्रपा",
        "01 अनु",
        "010 पञ्चा"
      ],
      "vaakya_pk": 37804,
      "vaakya_text": "स्वादोरित्थाविषूवताओहाउ।। मधोपिबन्तिगौरियाओहाउ।",
      "vaakya_sk": "030302070301010002",
      "permission": false
    },
    {
      "location": [
        "सा",
        "कौ",
        null,
        "07 काण्ड",
        "03 प्रपा"
      ],
      "vaakya_pk": 37805,
      "vaakya_text": "अथ षष्ठः खण्डः",
      "vaakya_sk": "030302070302",
      "permission": false
    },
    {
      "location": [
        "सा",
        "कौ",
        null,
        "07 काण्ड",
        "03 प्रपा",
        "02 अनु",
        "001 पञ्चा"
      ],
      "vaakya_pk": 37806,
      "vaakya_text": "39-1. त्रिषंधि।। बृहत्साम-रथन्तरम्-वामदेव्यम्। प्रजापतिः पथ्याबृहती इन्द्रः।।",
      "vaakya_sk": "030302070302001001",
      "permission": false
    },
    {
      "location": [
        "सा",
        "कौ",
        null,
        "07 काण्ड",
        "03 प्रपा",
        "02 अनु",
        "001 पञ्चा"
      ],
      "vaakya_pk": 37807,
      "vaakya_text": "औहोइत्वमिन्द्रप्रतूर्तिषूग़3ए।। अभाइवाइश्वाः। आसिस्पा234 र्द्धा।। श्रीः।। आशस्तिहाजनितावृ।",
      "vaakya_sk": "030302070302001002",
      "permission": false
    },
    {
      "location": [
        "सा",
        "कौ",
        null,
        "07 काण्ड",
        "03 प्रपा",
        "02 अनु",
        "002 पञ्चा"
      ],
      "vaakya_pk": 37808,
      "vaakya_text": "40-1. यज्ञसारथिः।। प्रजापतिर्बृहती सूर्यः।।",
      "vaakya_sk": "030302070302002001",
      "permission": false
    },
    {
      "location": [
        "सा",
        "कौ",
        null,
        "07 काण्ड",
        "03 प्रपा",
        "02 अनु",
        "002 पञ्चा"
      ],
      "vaakya_pk": 37809,
      "vaakya_text": "एबाण्मा।। हाअसिसूख़रिया। इडा। बॄ। हाउवा। आथा।। बाडा।। दित्यमहाख़असाइ। इडा। हरिः। हाउवा। आथा।। माह।। तेसतो महिमापनाख़इष्टमा। इडा। मतिः। हाउवा। आथा।। माह्ना।। देवमहाख़ असाइ।। इडा2345।।                            ◌दी-5। प-21। मा-12।। 12 (पा) 67।।",
      "vaakya_sk": "030302070302002002",
      "permission": false
    },
    {
      "location": [
        "सा",
        "कौ",
        null,
        "07 काण्ड",
        "03 प्रपा",
        "02 अनु",
        "003 पञ्चा"
      ],
      "vaakya_pk": 37810,
      "vaakya_text": "41-1. वृषा।। प्रजापतिरेकपदा त्रिष्टुब्विश्वेदेवाः।।",
      "vaakya_sk": "030302070302003001",
      "permission": false
    },
    {
      "location": [
        "सा",
        "कौ",
        null,
        "07 काण्ड",
        "03 प्रपा",
        "02 अनु",
        "003 पञ्चा"
      ],
      "vaakya_pk": 37811,
      "vaakya_text": "इमाओवा।(त्रिः)। इमाग़3। ओइ।(द्वे-द्विः)।। इमाग़3। ओ234 वा।। वृषाओवा।(त्रिः)। वृषाग़3। ओइ।(द्वे-द्विः)। वृषाग़3। ओ234वा। णंकृणावता। एकाओवा।(त्रिः)। एकाग़3। ओइ।(द्वे-द्विः)। एकाग़3। ओ234वा।। इन्मा2345म्।।                  ◌दी-35। प-29। मा-16।। 13 (भू) 68।।",
      "vaakya_sk": "030302070302003002",
      "permission": false
    },
    {
      "location": [
        "सा",
        "कौ",
        null,
        "07 काण्ड",
        "03 प्रपा",
        "02 अनु",
        "004 पञ्चा"
      ],
      "vaakya_pk": 37812,
      "vaakya_text": "42-1. एकवृषम्।। प्रजापतिरुष्णिगिन्द्रः।।",
      "vaakya_sk": "030302070302004001",
      "permission": false
    },
    {
      "location": [
        "सा",
        "कौ",
        null,
        "07 काण्ड",
        "03 प्रपा",
        "02 अनु",
        "004 पञ्चा"
      ],
      "vaakya_pk": 37813,
      "vaakya_text": "हाहिम्।(त्रिः)। योवा।(त्रिः)। योवाहाइ।(त्रिः)। यएकइद्विदयते। एक समैरयद्वृधे।। वसुमर्त्तायदाशुषे। एकसमैरयन्महे।। ईशानोअप्रतिष्कुतः। एकोवृषाविराजति।। इन्द्रोअंग। हाहिम्।(त्रिः)। योवा।(त्रिः)। योवाहाइ। (द्विः)। योवाढ़ग़3हाउ। वाग़3। ई2345।।",
      "vaakya_sk": "030302070302004002",
      "permission": false
    },
    {
      "location": [
        "सा",
        "कौ",
        null,
        "07 काण्ड",
        "03 प्रपा",
        "02 अनु",
        "005 पञ्चा"
      ],
      "vaakya_pk": 37814,
      "vaakya_text": "43-1. विद्रथं।। प्रजापतिः ककुबिन्द्रः।।",
      "vaakya_sk": "030302070302005001",
      "permission": false
    },
    {
      "location": [
        "सा",
        "कौ",
        null,
        "07 काण्ड",
        "03 प्रपा",
        "02 अनु",
        "005 पञ्चा"
      ],
      "vaakya_pk": 37815,
      "vaakya_text": "होवाहाइ। योनः।। होवाहाइ।(त्रिः)। औहोवाहाइ।(त्रिः)। इदामे। (द्विः)। पुराए। होवाहाइ।(त्रिः)। औहोवाहाइ।(त्रिः)। प्रवाए। स्यआए। निनाए। होवाहाइ।(त्रिः)। औहोवाहाइ।(त्रिः)। यतामे। उवाए। स्तुषाए।। होवाहाइ।(त्रिः)। औहोवाहाइ।(त्रिः)। सखाए। यआए। द्रमूए। तयाए। होवाहाइ।(त्रिः)। औहोवाहाइ।(द्विः)। औहोवाढ़ग़3हाउ। वाग़3।। हस्(स्थि) बृहन्नमा2345।।",
      "vaakya_sk": "030302070302005002",
      "permission": false
    },
    {
      "location": [
        "सा",
        "कौ",
        null,
        "07 काण्ड",
        "03 प्रपा",
        "02 अनु",
        "006 पञ्चा"
      ],
      "vaakya_pk": 37816,
      "vaakya_text": "44-1. अभ्रातृव्यम्।। प्रजापतिः ककुबिन्द्रः।।",
      "vaakya_sk": "030302070302006001",
      "permission": false
    },
    {
      "location": [
        "सा",
        "कौ",
        null,
        "07 काण्ड",
        "03 प्रपा",
        "02 अनु",
        "006 पञ्चा"
      ],
      "vaakya_pk": 37817,
      "vaakya_text": "हाउहाउहाउ। हुवेविराजस्वराजम्।(त्रिः)। हाओवा।(त्रिः)। हाग़3 ओ234वा।(द्विः)। हाउवा। महत्सामअजीजने। अभ्रातृव्योअनात्वम्।। महद्भद्रमजीजने। अनापिरिन्द्रजनुषासनाद।। स्यभ्रातृव्यमजीजने। युधेदा पित्वमिच्छसे।। हाउहाउहाउ। हुवेविराजस्वराजम्।(त्रिः)। हाओवा।",
      "vaakya_sk": "030302070302006002",
      "permission": false
    },
    {
      "location": [
        "सा",
        "कौ",
        null,
        "07 काण्ड",
        "03 प्रपा",
        "02 अनु",
        "007 पञ्चा"
      ],
      "vaakya_pk": 37818,
      "vaakya_text": "45-1. रैवते द्वे।। द्वयोः प्रजापतिर्गायत्रीन्द्रः।।",
      "vaakya_sk": "030302070302007001",
      "permission": false
    },
    {
      "location": [
        "सा",
        "कौ",
        null,
        "07 काण्ड",
        "03 प्रपा",
        "02 अनु",
        "007 पञ्चा"
      ],
      "vaakya_pk": 37819,
      "vaakya_text": "हाउरेवा।। तीर्ना। इहा। सधमादा2। हा31उवा23।। ई34 डा।। इन्द्राख़इसन्तू।। इहा। तुविवाजा2। हा31उवा23।। ई34डा।। क्षुमाख़न्तोया।। इहा। भिर्मदेमा2। हा31उवा23।। ई34डा।। \t\t\t      ◌दी-5। प-16। मा-7।। 17 (पे) 72।।",
      "vaakya_sk": "030302070302007002",
      "permission": false
    },
    {
      "location": [
        "सा",
        "कौ",
        null,
        "07 काण्ड",
        "03 प्रपा",
        "02 अनु",
        "008 पञ्चा"
      ],
      "vaakya_pk": 37820,
      "vaakya_text": "45-2.",
      "vaakya_sk": "030302070302008001",
      "permission": false
    },
    {
      "location": [
        "सा",
        "कौ",
        null,
        "07 काण्ड",
        "03 प्रपा",
        "02 अनु",
        "008 पञ्चा"
      ],
      "vaakya_pk": 37821,
      "vaakya_text": "रा।। वताख़इः। ना। इहा। औहौहो। इडा। सधाख़। मादाइ। इहा। औहौहो। इडा।। इन्द्राख़इ। सन्तू। इहा। औहौहो। इडा।। तुवाख़इ। वाजा। इहा। औहौहो। इडा।। क्षुमाख़। तोया। इहा। औहौहो। इडा।। भिर्म्माख़। देमा। इहा। औहौहो। इडा।। एरा। एबॄ। एरे2345।।",
      "vaakya_sk": "030302070302008002",
      "permission": false
    },
    {
      "location": [
        "सा",
        "कौ",
        null,
        "07 काण्ड",
        "03 प्रपा",
        "02 अनु",
        "009 पञ्चा"
      ],
      "vaakya_pk": 37822,
      "vaakya_text": "46-48-1. शाक्वरवर्णम्।। शाक्वरवर्णो गायत्री सोमः।।",
      "vaakya_sk": "030302070302009001",
      "permission": false
    },
    {
      "location": [
        "सा",
        "कौ",
        null,
        "07 काण्ड",
        "03 प्रपा",
        "02 अनु",
        "009 पञ्चा"
      ],
      "vaakya_pk": 37823,
      "vaakya_text": "एऊच्चा।। तेजातमन्धसोदिविसद्भूमियाख़ददाइ। इडा। उग्रशर्म महा1इश्राग़3वा।। श्रीः।। सान।। इन्द्राययज्यवेवरुणायमरूख़द्भिया। इडा। वरिवोवित्परा1इस्रा3वा।। श्रीः।। आइना।। विश्वान्यर्यआद्युम्ना निमानुषाख़णाम्। इडा।। सिषासन्तोवना23होइ।। माहाग़31उवा23।। इट्(स्थि)इडा2345।। \t\t\t\t\t◌दी-14। प-14। मा-13।। 19 (धि) 74।।",
      "vaakya_sk": "030302070302009002",
      "permission": false
    },
    {
      "location": [
        "सा",
        "कौ",
        null,
        "07 काण्ड",
        "03 प्रपा",
        "02 अनु",
        "010 पञ्चा"
      ],
      "vaakya_pk": 37824,
      "vaakya_text": "49-1. नित्यवत्साः।। प्रजापतिरत्यष्टिस्सोमः।।",
      "vaakya_sk": "030302070302010001",
      "permission": false
    },
    {
      "location": [
        "सा",
        "कौ",
        null,
        "07 काण्ड",
        "03 प्रपा",
        "02 अनु",
        "010 पञ्चा"
      ],
      "vaakya_pk": 37825,
      "vaakya_text": "एआया।। रुचाहरिण्यापुनानोविश्वाद्वेषासितरतिसयूख़ग्वभाइः। इडा। सूरोनसयू1ग्वाग़3भी।। धारा। पृष्ठस्यरोख़चताइ। इडा।। धारा। पृष्ठस्य रोख़चताइ। अथा।। धारा। पृष्ठस्यरोख़चताइ। इडा। पुनानोअरुषो1 हाग़3री। विश्वायद्रूपापरियासियाग़3। क्वाभी। सप्तास्येभिरा23हो। क्वाभिराग़31उवा23।। इट्(स्थि)इडा2345।।         ◌दी-17। प-19। मा-12।। 20 (झा) 75।।",
      "vaakya_sk": "030302070302010002",
      "permission": false
    },
    {
      "location": [
        "सा",
        "कौ",
        null,
        "07 काण्ड",
        "03 प्रपा",
        "02 अनु",
        "011 पञ्चा"
      ],
      "vaakya_pk": 37826,
      "vaakya_text": "50-1. वसिष्ठस्य च रथन्तरम्।। वसिष्ठो बृहतीशानरुद्रौ।।",
      "vaakya_sk": "030302070302011001",
      "permission": false
    },
    {
      "location": [
        "सा",
        "कौ",
        null,
        "07 काण्ड",
        "03 प्रपा",
        "02 अनु",
        "011 पञ्चा"
      ],
      "vaakya_pk": 37827,
      "vaakya_text": "आभित्वाशूरनोनुमोवा।। आदुग्धाइवधेनवईशानमस्यजगतः। सुवा 23र्दृशाम्।। आइशानमा23इन्द्राग़3।। तास्थू234षा। ओवा6। हाउवा।। अस्।।",
      "vaakya_sk": "030302070302011002",
      "permission": false
    },
    {
      "location": [
        "सा",
        "कौ",
        null,
        "07 काण्ड",
        "03 प्रपा",
        "02 अनु",
        "012 पञ्चा"
      ],
      "vaakya_pk": 37828,
      "vaakya_text": "51-1. जमदग्नेश्च सप्तहम्।। जमदग्निर्बृहतीन्द्रः।।",
      "vaakya_sk": "030302070302012001",
      "permission": false
    },
    {
      "location": [
        "सा",
        "कौ",
        null,
        "07 काण्ड",
        "03 प्रपा",
        "02 अनु",
        "012 पञ्चा"
      ],
      "vaakya_pk": 37829,
      "vaakya_text": "अयंवायाउ।(त्रिः)। त्वामिद्धाइ। हावामहाइ।।(त्रिः)। सातौवाजा। स्याकारवाः।।(त्रिः)। त्वांवृत्राइ।",
      "vaakya_sk": "030302070302012002",
      "permission": false
    },
    {
      "location": [
        "सा",
        "कौ",
        null,
        "07 काण्ड",
        "03 प्रपा"
      ],
      "vaakya_pk": 37830,
      "vaakya_text": "अथ सप्तमः खण्डः",
      "vaakya_sk": "030302070303",
      "permission": false
    },
    {
      "location": [
        "सा",
        "कौ",
        null,
        "07 काण्ड",
        "03 प्रपा",
        "03 अनु",
        "001 पञ्चा"
      ],
      "vaakya_pk": 37831,
      "vaakya_text": "52-1. पञ्च पविमन्ति (महासामानि) रुद्रसूक्तम्।। रुद्रस्त्रिष्टुबिन्द्रः।।",
      "vaakya_sk": "030302070303001001",
      "permission": false
    },
    {
      "location": [
        "सा",
        "कौ",
        null,
        "07 काण्ड",
        "03 प्रपा",
        "03 अनु",
        "001 पञ्चा"
      ],
      "vaakya_pk": 37832,
      "vaakya_text": "आक्रन्दयकुरुघोषंमहान्तहरीइन्द्रस्यभियोजयाशू।मर्म्माविधन्ददता मन्योअन्यशल्यात्मापततुश्लोकमच्छ।प्रयच्चक्रमराव्णेसनताअभ्यवर्त्तयत्। ज्योगित्तिस्रओहातैशयातैकेशवच्छिर।। \t\t(स्वरितम्-2। उदात्तम्-2। धारि-15। 23 (छु) 78।।",
      "vaakya_sk": "030302070303001002",
      "permission": false
    },
    {
      "location": [
        "सा",
        "कौ",
        null,
        "07 काण्ड",
        "03 प्रपा",
        "03 अनु",
        "002 पञ्चा"
      ],
      "vaakya_pk": 37833,
      "vaakya_text": "52-2.",
      "vaakya_sk": "030302070303002001",
      "permission": false
    },
    {
      "location": [
        "सा",
        "कौ",
        null,
        "07 काण्ड",
        "03 प्रपा",
        "03 अनु",
        "002 पञ्चा"
      ],
      "vaakya_pk": 37834,
      "vaakya_text": "आ। क्रन्दय। कुरु। घोषम्। महान्तम्।। हरीइति। इन्द्रस्य। अभि। योजय। आशूइति।। मर्माविधम्। मर्म-विधम्। ददताम्। अन्य। अन्-य। अन्यम्। अन्-यम्।। शल्यात्मा। शल्य-आत्मा। पततु। श्लोकम्। अच्छ।। प्र। यत्। चक्रम्। अराव्णे। अ-राव्णे।। सनतै। अभ्यवर्त्तयत्। अभि-अवर्त्तयत्।। ज्योक्। इत्। तिस्र। ओहातै।। शयातै। केशवत्। शिर।।",
      "vaakya_sk": "030302070303002002",
      "permission": false
    },
    {
      "location": [
        "सा",
        "कौ",
        null,
        "07 काण्ड",
        "03 प्रपा",
        "03 अनु",
        "003 पञ्चा"
      ],
      "vaakya_pk": 37835,
      "vaakya_text": "52-3.",
      "vaakya_sk": "030302070303003001",
      "permission": false
    },
    {
      "location": [
        "सा",
        "कौ",
        null,
        "07 काण्ड",
        "03 प्रपा",
        "03 अनु",
        "003 पञ्चा"
      ],
      "vaakya_pk": 37836,
      "vaakya_text": "आक्रन्दयोवा।। कुरुघोषंमहाख़। आन्ताख़म्। हरीइन्द्रस्याभियोजयाख़। आशूख़।। मर्म्माविधंददतामन्योख़। आन्याख़म्।। शल्यात्मा पततुश्लोकमा23। आ2ग़। च्छा234। औहोवा।। अस्।।   \t\t\t\t\t\t\t◌दी-12। प-12। मा-4।। 25 (छी) 80।।",
      "vaakya_sk": "030302070303003002",
      "permission": false
    },
    {
      "location": [
        "सा",
        "कौ",
        null,
        "07 काण्ड",
        "03 प्रपा",
        "03 अनु",
        "003 पञ्चा"
      ],
      "vaakya_pk": 37837,
      "vaakya_text": "हाउहाउहाउ। अस्।(त्रिः) फट्।(त्रिः)। मृस्।(त्रिः)। हस्।(त्रिः)। प्रायड़ग़2त्। चक्रड़2म्। आराज़2। आव्णाज़2इ।। सानड़2। ताअड़2। भ्यावड़2। तायड़2त्।। जीयोज़2क्। इत्तिड़2। स्राओज़2। हातैज़2।। शायाज़2। तैकेज़2। शावड़2त्। शाइरड़2। हाउहाउहाउ। अस्।(त्रिः)। फट्।(त्रिः)। मृस्।(त्रिः)। हस्।(द्विः)। हा234। औहोवा।। एअस्। एफट्। एमृस्। एहस्। ई2345।।",
      "vaakya_sk": "030302070303003003",
      "permission": false
    },
    {
      "location": [
        "सा",
        "कौ",
        null,
        "07 काण्ड",
        "03 प्रपा",
        "03 अनु",
        "004 पञ्चा"
      ],
      "vaakya_pk": 37838,
      "vaakya_text": "52-5. रुद्रोनुष्टुबिन्द्रः।।",
      "vaakya_sk": "030302070303004001",
      "permission": false
    },
    {
      "location": [
        "सा",
        "कौ",
        null,
        "07 काण्ड",
        "03 प्रपा",
        "03 अनु",
        "004 पञ्चा"
      ],
      "vaakya_pk": 37839,
      "vaakya_text": "अभ्याभू।(त्रिः)। प्रायड़2त्। चक्रड़2म्। आराज़2।",
      "vaakya_sk": "030302070303004002",
      "permission": false
    },
    {
      "location": [
        "सा",
        "कौ",
        null,
        "07 काण्ड",
        "03 प्रपा",
        "03 अनु",
        "005 पञ्चा"
      ],
      "vaakya_pk": 37840,
      "vaakya_text": "52-6. हरसी द्वे।। रुद्रोनुष्टुबिन्द्रः।।",
      "vaakya_sk": "030302070303005001",
      "permission": false
    },
    {
      "location": [
        "सा",
        "कौ",
        null,
        "07 काण्ड",
        "03 प्रपा",
        "03 अनु",
        "005 पञ्चा"
      ],
      "vaakya_pk": 37841,
      "vaakya_text": "हाउहाउहाउ। क्षुरोहरोहरोहरः।(त्रिः)। वृश्चप्रवृश्चप्रच्छिन्धि।(त्रिः)। हाउहाउहाउवा। प्रयच्चक्रमराव्णे।। सनताअभ्यवर्त्तयत्।। ज्योगित्तिस्र ओहातै।। शयातैकेशवच्छिरः। हाउहाउहाउ। क्षुरोहरोहरोहरः।(त्रिः)। वृश्च प्रवृश्चप्रच्छिन्धि।(त्रिः)। हाउहाउहाउवा।। ए। वृश्चप्रवृश्चप्रच्छिन्धि। (द्वे-द्विः)। ए। वृश्चप्रवृश्चप्रच्छिन्धी2345।। \t\t\t◌दी-37। प-26। मा-22।। 28 (चा) 83।।",
      "vaakya_sk": "030302070303005002",
      "permission": false
    },
    {
      "location": [
        "सा",
        "कौ",
        null,
        "07 काण्ड",
        "03 प्रपा",
        "03 अनु",
        "006 पञ्चा"
      ],
      "vaakya_pk": 37842,
      "vaakya_text": "53-1. मृत्योर्हरः लोकानां शान्तिरुत्तमम्।।",
      "vaakya_sk": "030302070303006001",
      "permission": false
    },
    {
      "location": [
        "सा",
        "कौ",
        null,
        "07 काण्ड",
        "03 प्रपा",
        "03 अनु",
        "006 पञ्चा"
      ],
      "vaakya_pk": 37843,
      "vaakya_text": "हाउहाउहाउ। वयोबृहदृतहविर्भद्रास्वधास्वयस्कृण्वइषमूर्ज रजस्सुवः। हिम्।(त्रिः)। हो।(त्रिः)। ह।(द्विः)। ह234। औहोवा। अभित्वाशूरनोनुमोहस्।। अदुग्धाइवधेनवोहस्।। ईशानमस्यजगतस्व र्दृशहस्।। ईशानमिन्द्रतस्थुषोहस्। हाउहाउहाउ। वयोबृहदृतहविर्भद्रा स्वधास्वयस्कृण्वइषमूर्जरजस्सुवः। हिम्।(त्रिः)। हो।(त्रिः)। ह। (द्विः)। ह234। औहोवा।। ए। वाक्। ए। इडा। ए। सुवः। ए। बृहत्। ए। भा। ए। अर्कमर्चतदेवावृधहस्।।",
      "vaakya_sk": "030302070303006002",
      "permission": false
    },
    {
      "location": [
        "सा",
        "कौ",
        null,
        "07 काण्ड",
        "03 प्रपा",
        "03 अनु",
        "007 पञ्चा"
      ],
      "vaakya_pk": 37844,
      "vaakya_text": "54-1. पञ्चनिधनं वामदेव्यम्।। वामदेवो गायत्री विश्वेदेवाः।।",
      "vaakya_sk": "030302070303007001",
      "permission": false
    },
    {
      "location": [
        "सा",
        "कौ",
        null,
        "07 काण्ड",
        "03 प्रपा",
        "03 अनु",
        "007 पञ्चा"
      ],
      "vaakya_pk": 37845,
      "vaakya_text": "होवाग़3हाग़3। आ2ग़इ। हिया345। हाउहाउहाउ। एहियाहाउ। (द्विः)। एहियाग़34। औहोवा। इहप्रजामिहरयिरराणोहस्। होवाग़3हाग़3। आ2ग़इ। हिया345। हाउहाउहाउ। एहियाहाउ।(त्रिः)। कयानश्चाइ। त्रय़आ2ग़भू234वात्। होवाग़3हाग़3। आ2ग़इ। हिया345। हाउहाउहाउ। एहियाहाउ।(द्विः)। एहियाग़34। औहोवा। रायस्पोशायसुकृतायभूयसेहस्। होवाग़3हाग़3। आ2ग़इ। हिया345। हाउहाउहाउ। एहियाहाउ।(त्रिः)। ऊताइसदा। वार्द्धस्सा234खा।। होवाग़3हाग़3। आ2ग़इ। हिया345। हाउहाउहाउ। एहियाहाउ।(द्विः)। एहियाग़34। औहोवा। आगन्वाममिदं बृहद्धस्। होवाग़3हाग़3। आ2ग़इ। हिया345। हाउहाउहाउ। एहियाहाउ। (त्रिः)। कयाशचाइ। ष्ठय़या2ग़वा234र्त्ता।। होवाग़3हाग़3। आ2ग़इ। हिया 345। हाउहाउहाउ। एहियाहाउ।(द्विः)। एहियाग़34। औहोवा। इदंवा ममिदंबृहद्धस्। होवाग़3हाग़3। आ2ग़इ। हिया345। हाउहाउहाउ। एहि याहाउ।(त्रिः)। कयाशचाइ। ष्ठय़या2ग़वा234र्त्ता।। होवाग़3हाग़3। आ2ग़इ। हिया345। हाउहाउहाउ। एहियाहाउ।(द्विः)। एहियाग़34। औहोवा। चराचरायबृहतइदंवाममिदंबृहद्धस्।।",
      "vaakya_sk": "030302070303007002",
      "permission": false
    },
    {
      "location": [
        "सा",
        "कौ",
        null,
        "07 काण्ड",
        "03 प्रपा",
        "03 अनु",
        "008 पञ्चा"
      ],
      "vaakya_pk": 37846,
      "vaakya_text": "55-1. इन्द्रस्य महावैराजं वसिष्ठस्य वा।। इन्द्रो विराडिन्द्रः।।",
      "vaakya_sk": "030302070303008001",
      "permission": false
    },
    {
      "location": [
        "सा",
        "कौ",
        null,
        "07 काण्ड",
        "03 प्रपा",
        "03 अनु",
        "008 पञ्चा"
      ],
      "vaakya_pk": 37847,
      "vaakya_text": "होइयाहोइयाहोइयाग़343पिब।। मत्स्वाहाउ। ओजोहाउ। सहोहाउ। बलहाउ।",
      "vaakya_sk": "030302070303008002",
      "permission": false
    },
    {
      "location": [
        "सा",
        "कौ",
        null,
        "07 काण्ड",
        "03 प्रपा",
        "03 अनु",
        "009 पञ्चा"
      ],
      "vaakya_pk": 37848,
      "vaakya_text": "56-1. अग्नेश्च प्रियम्।। अग्निर्गायत्र्यग्निः।।",
      "vaakya_sk": "030302070303009001",
      "permission": false
    },
    {
      "location": [
        "सा",
        "कौ",
        null,
        "07 काण्ड",
        "03 प्रपा",
        "03 अनु",
        "009 पञ्चा"
      ],
      "vaakya_pk": 37849,
      "vaakya_text": "हाउहाउहाउ। प्रियहोइ।(त्रिः)। प्रियमोइ।(त्रिः)। अग्नआयाहिग़3 वाइता1याख़इ।। गृणानोहव्यग़3दाता1याख़इ।। निहोतासत्सिग़3बार्हा 1इषी23।। हाउहाउहाउ। प्रियहोइ।(त्रिः)। प्रियमोइ।(द्विः)। प्रि। या2ग़म्। आ234। औहोवा।। ए। प्रियम्।(द्वे-त्रिः)। ए। ब्राह्मणानां यन्मनस्तन्मयिब्राह्मणानाम्। ए। पशूनांयन्मनस्तन्मयिपशूनाम्। ए। योषितांयन्मनस्तन्मयियोषिता2345म्।। \t\t◌दी-33। प-32। मा-29।। 32 (ठो) 87।।",
      "vaakya_sk": "030302070303009002",
      "permission": false
    },
    {
      "location": [
        "सा",
        "कौ",
        null,
        "07 काण्ड",
        "03 प्रपा",
        "03 अनु",
        "010 पञ्चा"
      ],
      "vaakya_pk": 37850,
      "vaakya_text": "57-1. सर्पसाम कल्माषं वा वामदेव्यम्।। प्रजापतिर्गायत्री विश्वेदेवाः।।",
      "vaakya_sk": "030302070303010001",
      "permission": false
    },
    {
      "location": [
        "सा",
        "कौ",
        null,
        "07 काण्ड",
        "03 प्रपा",
        "03 अनु",
        "010 पञ्चा"
      ],
      "vaakya_pk": 37851,
      "vaakya_text": "वीहायवाइ।(त्रिः)। वीहायवाइ।(त्रिः)। कयानश्चाइ। त्रय़आ2ग़भू234 वात्।। ऊताइसदा।",
      "vaakya_sk": "030302070303010002",
      "permission": false
    },
    {
      "location": [
        "सा",
        "कौ",
        null,
        "07 काण्ड",
        "03 प्रपा",
        "03 अनु",
        "011 पञ्चा"
      ],
      "vaakya_pk": 37852,
      "vaakya_text": "58-1. स्वर्ग्यम्, सेतुषाम पुरुषगतिर्वा।। प्रजापतिस्त्रिष्टुबात्मा।।",
      "vaakya_sk": "030302070303011001",
      "permission": false
    },
    {
      "location": [
        "सा",
        "कौ",
        null,
        "07 काण्ड",
        "03 प्रपा",
        "03 अनु",
        "011 पञ्चा"
      ],
      "vaakya_pk": 37853,
      "vaakya_text": "हाउहाउहाउ। सेतूस्तर।(त्रिः)। दुस्त। रान्।(द्वे-त्रिः)। दानेनादानम्। (त्रिः)। हाउहाउहाउ। अहमस्मिप्रथमजाऋता23स्या345।। हाउहाउ हाउ। सेतूस्तर।(त्रिः)। दुस्त। रान्।(द्वे-त्रिः)। अक्रोधेनक्रोधम्।(द्विः)। अक्रोधेनक्रोधम्। हाउहाउहाउ। पूर्वन्देवेभ्योअमृतस्यना23माग़345।। हाउहाउहाउ। सेतूस्तर।(त्रिः)। दुस्त। रान्।(द्वे-त्रिः)। श्रद्धयाश्रद्धाम्। (त्रिः)। हाउहाउहाउ। योमाददातिसइदेवमा23वाग़345त्।। हाउहाउहाउ। सेतूस्तर।(त्रिः)। दुस्त। रान्।(द्वे-त्रिः)। सत्येनानृतम्।(त्रिः)। हाउहाउहाउ। अहमन्नमन्नमदन्तमा23द्मीग़345।। हाउहाउहाउवा। एषागतिः। (त्रिः)। एतदमृतम्।(त्रिः)। स्वर्गच्छ।(त्रिः)। ज्योतिर्गच्छ।(त्रिः)। सेतू स्तीर्त्वाचतुरा2345।।",
      "vaakya_sk": "030302070303011002",
      "permission": false
    }
  ],
  "meta": {
    "source_id": "03030207_प्रकृति,_आरण्यकगानम्_-_(03030207)_काण्डम्",
    "file_name": "03030207_प्रकृति,_आरण्यकगानम्_-_(03030207)_काण्डम्.json",
    "total_records": 0
  }
}